{"@xmlns:gco": "http://www.isotc211.org/2005/gco", "@xmlns:gfc": "http://www.isotc211.org/2005/gfc", "@xmlns:gmd": "http://www.isotc211.org/2005/gmd", "@xmlns:xsi": "http://www.w3.org/2001/XMLSchema-instance", "@uuid": "a2d42021-3d84-4403-9153-63a1402dfb99", "@xsi:schemaLocation": "http://www.isotc211.org/2005/gfc http://www.isotc211.org/2005/gfc/gfc.xsd", "gfc:name": {"gco:CharacterString": {"@xmlns:gco": "http://www.isotc211.org/2005/gco", "#text": "a2d42021-3d84-4403-9153-63a1402dfb99"}}, "gfc:scope": {"gco:CharacterString": {"@xmlns:gco": "http://www.isotc211.org/2005/gco", "#text": "http://url.of.your.document"}}, "gfc:fieldOfApplication": {"gco:CharacterString": {"@xmlns:gco": "http://www.isotc211.org/2005/gco", "#text": "Dictionnaire de donn\u00e9es pour ..."}}, "gfc:versionNumber": {"gco:CharacterString": null}, "gfc:versionDate": {"gco:Date": {"@xmlns:gco": "http://www.isotc211.org/2005/gco", "#text": "2011-12-15T16:16:42"}}, "gfc:producer": {"gmd:CI_ResponsibleParty": {"@xmlns:gmd": "http://www.isotc211.org/2005/gmd", "gmd:individualName": {"gco:CharacterString": null}, "gmd:organisationName": {"gco:CharacterString": null}, "gmd:positionName": {"gco:CharacterString": null}, "gmd:contactInfo": {"gmd:CI_Contact": {"gmd:phone": {"gmd:CI_Telephone": {"gmd:voice": {"gco:CharacterString": null}, "gmd:facsimile": {"gco:CharacterString": null}}}, "gmd:address": {"gmd:CI_Address": {"gmd:deliveryPoint": {"gco:CharacterString": null}, "gmd:city": {"gco:CharacterString": null}, "gmd:administrativeArea": {"gco:CharacterString": null}, "gmd:postalCode": {"gco:CharacterString": null}, "gmd:country": {"gco:CharacterString": null}, "gmd:electronicMailAddress": {"gco:CharacterString": null}}}}}, "gmd:role": {"gmd:CI_RoleCode": {"@codeListValue": "principalInvestigator", "@codeList": "CI_RoleCode"}}}}, "gfc:featureType": {"gfc:FC_FeatureType": {"gfc:typeName": {"gco:LocalName": {"@xmlns:gco": "http://www.isotc211.org/2005/gco", "#text": "Table"}}, "gfc:definition": {"gco:CharacterString": {"@xmlns:gco": "http://www.isotc211.org/2005/gco", "#text": "Definition de la table d'attributs"}}, "gfc:isAbstract": {"gco:Boolean": {"@xmlns:gco": "http://www.isotc211.org/2005/gco", "#text": "false"}}, "gfc:aliases": {"gco:LocalName": null}, "gfc:featureCatalogue": null, "gfc:carrierOfCharacteristics": [{"gfc:FC_FeatureAttribute": {"gfc:memberName": {"gco:LocalName": {"@xmlns:gco": "http://www.isotc211.org/2005/gco", "#text": "id"}}, "gfc:definition": {"gco:CharacterString": null}, "gfc:cardinality": {"gco:Multiplicity": {"@xmlns:gco": "http://www.isotc211.org/2005/gco", "gco:range": {"gco:MultiplicityRange": {"gco:lower": {"gco:Integer": "0"}, "gco:upper": {"gco:UnlimitedInteger": {"@xmlns:xsi": "http://www.w3.org/2001/XMLSchema-instance", "@isInfinite": "true", "@xsi:nil": "true"}}}}}}, "gfc:featureType": null, "gfc:valueMeasurementUnit": {"gml:UnitDefinition": {"@xmlns:gml": "http://www.opengis.net/gml", "@gml:id": null, "gml:identifier": {"@codeSpace": "unknown"}}}, "gfc:valueType": {"gco:TypeName": {"@xmlns:gco": "http://www.isotc211.org/2005/gco", "gco:aName": {"gco:CharacterString": "Chaine de caract\u00e8res"}}}}}, {"gfc:FC_FeatureAttribute": {"gfc:memberName": {"gco:LocalName": {"@xmlns:gco": "http://www.isotc211.org/2005/gco", "#text": "prec_plani"}}, "gfc:definition": {"gco:CharacterString": null}, "gfc:cardinality": {"gco:Multiplicity": {"@xmlns:gco": "http://www.isotc211.org/2005/gco", "gco:range": {"gco:MultiplicityRange": {"gco:lower": {"gco:Integer": "0"}, "gco:upper": {"gco:UnlimitedInteger": {"@xmlns:xsi": "http://www.w3.org/2001/XMLSchema-instance", "@isInfinite": "true", "@xsi:nil": "true"}}}}}}, "gfc:featureType": null, "gfc:valueMeasurementUnit": {"gml:UnitDefinition": {"@xmlns:gml": "http://www.opengis.net/gml", "@gml:id": null, "gml:identifier": {"@codeSpace": "unknown"}}}, "gfc:valueType": {"gco:TypeName": {"@xmlns:gco": "http://www.isotc211.org/2005/gco", "gco:aName": {"gco:CharacterString": "Num\u00e9rique"}}}}}, {"gfc:FC_FeatureAttribute": {"gfc:memberName": {"gco:LocalName": {"@xmlns:gco": "http://www.isotc211.org/2005/gco", "#text": "prec_alti"}}, "gfc:definition": {"gco:CharacterString": null}, "gfc:cardinality": {"gco:Multiplicity": {"@xmlns:gco": "http://www.isotc211.org/2005/gco", "gco:range": {"gco:MultiplicityRange": {"gco:lower": {"gco:Integer": "0"}, "gco:upper": {"gco:UnlimitedInteger": {"@xmlns:xsi": "http://www.w3.org/2001/XMLSchema-instance", "@isInfinite": "true", "@xsi:nil": "true"}}}}}}, "gfc:featureType": null, "gfc:valueMeasurementUnit": {"gml:UnitDefinition": {"@xmlns:gml": "http://www.opengis.net/gml", "@gml:id": null, "gml:identifier": {"@codeSpace": "unknown"}}}, "gfc:valueType": {"gco:TypeName": {"@xmlns:gco": "http://www.isotc211.org/2005/gco", "gco:aName": {"gco:CharacterString": "Num\u00e9rique"}}}}}, {"gfc:FC_FeatureAttribute": {"gfc:memberName": {"gco:LocalName": {"@xmlns:gco": "http://www.isotc211.org/2005/gco", "#text": "nature"}}, "gfc:definition": {"gco:CharacterString": null}, "gfc:cardinality": {"gco:Multiplicity": {"@xmlns:gco": "http://www.isotc211.org/2005/gco", "gco:range": {"gco:MultiplicityRange": {"gco:lower": {"gco:Integer": "0"}, "gco:upper": {"gco:UnlimitedInteger": {"@xmlns:xsi": "http://www.w3.org/2001/XMLSchema-instance", "@isInfinite": "true", "@xsi:nil": "true"}}}}}}, "gfc:featureType": null, "gfc:valueMeasurementUnit": {"gml:UnitDefinition": {"@xmlns:gml": "http://www.opengis.net/gml", "@gml:id": null, "gml:identifier": {"@codeSpace": "unknown"}}}, "gfc:valueType": {"gco:TypeName": {"@xmlns:gco": "http://www.isotc211.org/2005/gco", "gco:aName": {"gco:CharacterString": "Chaine de caract\u00e8res"}}}}}, {"gfc:FC_FeatureAttribute": {"gfc:memberName": {"gco:LocalName": {"@xmlns:gco": "http://www.isotc211.org/2005/gco", "#text": "numero"}}, "gfc:definition": {"gco:CharacterString": null}, "gfc:cardinality": {"gco:Multiplicity": {"@xmlns:gco": "http://www.isotc211.org/2005/gco", "gco:range": {"gco:MultiplicityRange": {"gco:lower": {"gco:Integer": "0"}, "gco:upper": {"gco:UnlimitedInteger": {"@xmlns:xsi": "http://www.w3.org/2001/XMLSchema-instance", "@isInfinite": "true", "@xsi:nil": "true"}}}}}}, "gfc:featureType": null, "gfc:valueMeasurementUnit": {"gml:UnitDefinition": {"@xmlns:gml": "http://www.opengis.net/gml", "@gml:id": null, "gml:identifier": {"@codeSpace": "unknown"}}}, "gfc:valueType": {"gco:TypeName": {"@xmlns:gco": "http://www.isotc211.org/2005/gco", "gco:aName": {"gco:CharacterString": "Chaine de caract\u00e8res"}}}}}, {"gfc:FC_FeatureAttribute": {"gfc:memberName": {"gco:LocalName": {"@xmlns:gco": "http://www.isotc211.org/2005/gco", "#text": "nom_rue_g"}}, "gfc:definition": {"gco:CharacterString": null}, "gfc:cardinality": {"gco:Multiplicity": {"@xmlns:gco": "http://www.isotc211.org/2005/gco", "gco:range": {"gco:MultiplicityRange": {"gco:lower": {"gco:Integer": "0"}, "gco:upper": {"gco:UnlimitedInteger": {"@xmlns:xsi": "http://www.w3.org/2001/XMLSchema-instance", "@isInfinite": "true", "@xsi:nil": "true"}}}}}}, "gfc:featureType": null, "gfc:valueMeasurementUnit": {"gml:UnitDefinition": {"@xmlns:gml": "http://www.opengis.net/gml", "@gml:id": null, "gml:identifier": {"@codeSpace": "unknown"}}}, "gfc:valueType": {"gco:TypeName": {"@xmlns:gco": "http://www.isotc211.org/2005/gco", "gco:aName": {"gco:CharacterString": "Chaine de caract\u00e8res"}}}}}, {"gfc:FC_FeatureAttribute": {"gfc:memberName": {"gco:LocalName": {"@xmlns:gco": "http://www.isotc211.org/2005/gco", "#text": "nom_rue_d"}}, "gfc:definition": {"gco:CharacterString": null}, "gfc:cardinality": {"gco:Multiplicity": {"@xmlns:gco": "http://www.isotc211.org/2005/gco", "gco:range": {"gco:MultiplicityRange": {"gco:lower": {"gco:Integer": "0"}, "gco:upper": {"gco:UnlimitedInteger": {"@xmlns:xsi": "http://www.w3.org/2001/XMLSchema-instance", "@isInfinite": "true", "@xsi:nil": "true"}}}}}}, "gfc:featureType": null, "gfc:valueMeasurementUnit": {"gml:UnitDefinition": {"@xmlns:gml": "http://www.opengis.net/gml", "@gml:id": null, "gml:identifier": {"@codeSpace": "unknown"}}}, "gfc:valueType": {"gco:TypeName": {"@xmlns:gco": "http://www.isotc211.org/2005/gco", "gco:aName": {"gco:CharacterString": "Chaine de caract\u00e8res"}}}}}, {"gfc:FC_FeatureAttribute": {"gfc:memberName": {"gco:LocalName": {"@xmlns:gco": "http://www.isotc211.org/2005/gco", "#text": "importance"}}, "gfc:definition": {"gco:CharacterString": null}, "gfc:cardinality": {"gco:Multiplicity": {"@xmlns:gco": "http://www.isotc211.org/2005/gco", "gco:range": {"gco:MultiplicityRange": {"gco:lower": {"gco:Integer": "0"}, "gco:upper": {"gco:UnlimitedInteger": {"@xmlns:xsi": "http://www.w3.org/2001/XMLSchema-instance", "@isInfinite": "true", "@xsi:nil": "true"}}}}}}, "gfc:featureType": null, "gfc:valueMeasurementUnit": {"gml:UnitDefinition": {"@xmlns:gml": "http://www.opengis.net/gml", "@gml:id": null, "gml:identifier": {"@codeSpace": "unknown"}}}, "gfc:valueType": {"gco:TypeName": {"@xmlns:gco": "http://www.isotc211.org/2005/gco", "gco:aName": {"gco:CharacterString": "Chaine de caract\u00e8res"}}}}}, {"gfc:FC_FeatureAttribute": {"gfc:memberName": {"gco:LocalName": {"@xmlns:gco": "http://www.isotc211.org/2005/gco", "#text": "cl_admin"}}, "gfc:definition": {"gco:CharacterString": null}, "gfc:cardinality": {"gco:Multiplicity": {"@xmlns:gco": "http://www.isotc211.org/2005/gco", "gco:range": {"gco:MultiplicityRange": {"gco:lower": {"gco:Integer": "0"}, "gco:upper": {"gco:UnlimitedInteger": {"@xmlns:xsi": "http://www.w3.org/2001/XMLSchema-instance", "@isInfinite": "true", "@xsi:nil": "true"}}}}}}, "gfc:featureType": null, "gfc:valueMeasurementUnit": {"gml:UnitDefinition": {"@xmlns:gml": "http://www.opengis.net/gml", "@gml:id": null, "gml:identifier": {"@codeSpace": "unknown"}}}, "gfc:valueType": {"gco:TypeName": {"@xmlns:gco": "http://www.isotc211.org/2005/gco", "gco:aName": {"gco:CharacterString": "Chaine de caract\u00e8res"}}}}}, {"gfc:FC_FeatureAttribute": {"gfc:memberName": {"gco:LocalName": {"@xmlns:gco": "http://www.isotc211.org/2005/gco", "#text": "gestion"}}, "gfc:definition": {"gco:CharacterString": null}, "gfc:cardinality": {"gco:Multiplicity": {"@xmlns:gco": "http://www.isotc211.org/2005/gco", "gco:range": {"gco:MultiplicityRange": {"gco:lower": {"gco:Integer": "0"}, "gco:upper": {"gco:UnlimitedInteger": {"@xmlns:xsi": "http://www.w3.org/2001/XMLSchema-instance", "@isInfinite": "true", "@xsi:nil": "true"}}}}}}, "gfc:featureType": null, "gfc:valueMeasurementUnit": {"gml:UnitDefinition": {"@xmlns:gml": "http://www.opengis.net/gml", "@gml:id": null, "gml:identifier": {"@codeSpace": "unknown"}}}, "gfc:valueType": {"gco:TypeName": {"@xmlns:gco": "http://www.isotc211.org/2005/gco", "gco:aName": {"gco:CharacterString": "Chaine de caract\u00e8res"}}}}}, {"gfc:FC_FeatureAttribute": {"gfc:memberName": {"gco:LocalName": {"@xmlns:gco": "http://www.isotc211.org/2005/gco", "#text": "mise_serv"}}, "gfc:definition": {"gco:CharacterString": null}, "gfc:cardinality": {"gco:Multiplicity": {"@xmlns:gco": "http://www.isotc211.org/2005/gco", "gco:range": {"gco:MultiplicityRange": {"gco:lower": {"gco:Integer": "0"}, "gco:upper": {"gco:UnlimitedInteger": {"@xmlns:xsi": "http://www.w3.org/2001/XMLSchema-instance", "@isInfinite": "true", "@xsi:nil": "true"}}}}}}, "gfc:featureType": null, "gfc:valueMeasurementUnit": {"gml:UnitDefinition": {"@xmlns:gml": "http://www.opengis.net/gml", "@gml:id": null, "gml:identifier": {"@codeSpace": "unknown"}}}, "gfc:valueType": {"gco:TypeName": {"@xmlns:gco": "http://www.isotc211.org/2005/gco", "gco:aName": {"gco:CharacterString": "Chaine de caract\u00e8res"}}}}}, {"gfc:FC_FeatureAttribute": {"gfc:memberName": {"gco:LocalName": {"@xmlns:gco": "http://www.isotc211.org/2005/gco", "#text": "it_vert"}}, "gfc:definition": {"gco:CharacterString": null}, "gfc:cardinality": {"gco:Multiplicity": {"@xmlns:gco": "http://www.isotc211.org/2005/gco", "gco:range": {"gco:MultiplicityRange": {"gco:lower": {"gco:Integer": "0"}, "gco:upper": {"gco:UnlimitedInteger": {"@xmlns:xsi": "http://www.w3.org/2001/XMLSchema-instance", "@isInfinite": "true", "@xsi:nil": "true"}}}}}}, "gfc:featureType": null, "gfc:valueMeasurementUnit": {"gml:UnitDefinition": {"@xmlns:gml": "http://www.opengis.net/gml", "@gml:id": null, "gml:identifier": {"@codeSpace": "unknown"}}}, "gfc:valueType": {"gco:TypeName": {"@xmlns:gco": "http://www.isotc211.org/2005/gco", "gco:aName": {"gco:CharacterString": "Chaine de caract\u00e8res"}}}}}, {"gfc:FC_FeatureAttribute": {"gfc:memberName": {"gco:LocalName": {"@xmlns:gco": "http://www.isotc211.org/2005/gco", "#text": "it_europ"}}, "gfc:definition": {"gco:CharacterString": null}, "gfc:cardinality": {"gco:Multiplicity": {"@xmlns:gco": "http://www.isotc211.org/2005/gco", "gco:range": {"gco:MultiplicityRange": {"gco:lower": {"gco:Integer": "0"}, "gco:upper": {"gco:UnlimitedInteger": {"@xmlns:xsi": "http://www.w3.org/2001/XMLSchema-instance", "@isInfinite": "true", "@xsi:nil": "true"}}}}}}, "gfc:featureType": null, "gfc:valueMeasurementUnit": {"gml:UnitDefinition": {"@xmlns:gml": "http://www.opengis.net/gml", "@gml:id": null, "gml:identifier": {"@codeSpace": "unknown"}}}, "gfc:valueType": {"gco:TypeName": {"@xmlns:gco": "http://www.isotc211.org/2005/gco", "gco:aName": {"gco:CharacterString": "Chaine de caract\u00e8res"}}}}}, {"gfc:FC_FeatureAttribute": {"gfc:memberName": {"gco:LocalName": {"@xmlns:gco": "http://www.isotc211.org/2005/gco", "#text": "fictif"}}, "gfc:definition": {"gco:CharacterString": null}, "gfc:cardinality": {"gco:Multiplicity": {"@xmlns:gco": "http://www.isotc211.org/2005/gco", "gco:range": {"gco:MultiplicityRange": {"gco:lower": {"gco:Integer": "0"}, "gco:upper": {"gco:UnlimitedInteger": {"@xmlns:xsi": "http://www.w3.org/2001/XMLSchema-instance", "@isInfinite": "true", "@xsi:nil": "true"}}}}}}, "gfc:featureType": null, "gfc:valueMeasurementUnit": {"gml:UnitDefinition": {"@xmlns:gml": "http://www.opengis.net/gml", "@gml:id": null, "gml:identifier": {"@codeSpace": "unknown"}}}, "gfc:valueType": {"gco:TypeName": {"@xmlns:gco": "http://www.isotc211.org/2005/gco", "gco:aName": {"gco:CharacterString": "Chaine de caract\u00e8res"}}}}}, {"gfc:FC_FeatureAttribute": {"gfc:memberName": {"gco:LocalName": {"@xmlns:gco": "http://www.isotc211.org/2005/gco", "#text": "franchisst"}}, "gfc:definition": {"gco:CharacterString": null}, "gfc:cardinality": {"gco:Multiplicity": {"@xmlns:gco": "http://www.isotc211.org/2005/gco", "gco:range": {"gco:MultiplicityRange": {"gco:lower": {"gco:Integer": "0"}, "gco:upper": {"gco:UnlimitedInteger": {"@xmlns:xsi": "http://www.w3.org/2001/XMLSchema-instance", "@isInfinite": "true", "@xsi:nil": "true"}}}}}}, "gfc:featureType": null, "gfc:valueMeasurementUnit": {"gml:UnitDefinition": {"@xmlns:gml": "http://www.opengis.net/gml", "@gml:id": null, "gml:identifier": {"@codeSpace": "unknown"}}}, "gfc:valueType": {"gco:TypeName": {"@xmlns:gco": "http://www.isotc211.org/2005/gco", "gco:aName": {"gco:CharacterString": "Chaine de caract\u00e8res"}}}}}, {"gfc:FC_FeatureAttribute": {"gfc:memberName": {"gco:LocalName": {"@xmlns:gco": "http://www.isotc211.org/2005/gco", "#text": "largeur"}}, "gfc:definition": {"gco:CharacterString": null}, "gfc:cardinality": {"gco:Multiplicity": {"@xmlns:gco": "http://www.isotc211.org/2005/gco", "gco:range": {"gco:MultiplicityRange": {"gco:lower": {"gco:Integer": "0"}, "gco:upper": {"gco:UnlimitedInteger": {"@xmlns:xsi": "http://www.w3.org/2001/XMLSchema-instance", "@isInfinite": "true", "@xsi:nil": "true"}}}}}}, "gfc:featureType": null, "gfc:valueMeasurementUnit": {"gml:UnitDefinition": {"@xmlns:gml": "http://www.opengis.net/gml", "@gml:id": null, "gml:identifier": {"@codeSpace": "unknown"}}}, "gfc:valueType": {"gco:TypeName": {"@xmlns:gco": "http://www.isotc211.org/2005/gco", "gco:aName": {"gco:CharacterString": "Num\u00e9rique"}}}}}, {"gfc:FC_FeatureAttribute": {"gfc:memberName": {"gco:LocalName": {"@xmlns:gco": "http://www.isotc211.org/2005/gco", "#text": "nom_iti"}}, "gfc:definition": {"gco:CharacterString": null}, "gfc:cardinality": {"gco:Multiplicity": {"@xmlns:gco": "http://www.isotc211.org/2005/gco", "gco:range": {"gco:MultiplicityRange": {"gco:lower": {"gco:Integer": "0"}, "gco:upper": {"gco:UnlimitedInteger": {"@xmlns:xsi": "http://www.w3.org/2001/XMLSchema-instance", "@isInfinite": "true", "@xsi:nil": "true"}}}}}}, "gfc:featureType": null, "gfc:valueMeasurementUnit": {"gml:UnitDefinition": {"@xmlns:gml": "http://www.opengis.net/gml", "@gml:id": null, "gml:identifier": {"@codeSpace": "unknown"}}}, "gfc:valueType": {"gco:TypeName": {"@xmlns:gco": "http://www.isotc211.org/2005/gco", "gco:aName": {"gco:CharacterString": "Chaine de caract\u00e8res"}}}}}, {"gfc:FC_FeatureAttribute": {"gfc:memberName": {"gco:LocalName": {"@xmlns:gco": "http://www.isotc211.org/2005/gco", "#text": "nb_voies"}}, "gfc:definition": {"gco:CharacterString": null}, "gfc:cardinality": {"gco:Multiplicity": {"@xmlns:gco": "http://www.isotc211.org/2005/gco", "gco:range": {"gco:MultiplicityRange": {"gco:lower": {"gco:Integer": "0"}, "gco:upper": {"gco:UnlimitedInteger": {"@xmlns:xsi": "http://www.w3.org/2001/XMLSchema-instance", "@isInfinite": "true", "@xsi:nil": "true"}}}}}}, "gfc:featureType": null, "gfc:valueMeasurementUnit": {"gml:UnitDefinition": {"@xmlns:gml": "http://www.opengis.net/gml", "@gml:id": null, "gml:identifier": {"@codeSpace": "unknown"}}}, "gfc:valueType": {"gco:TypeName": {"@xmlns:gco": "http://www.isotc211.org/2005/gco", "gco:aName": {"gco:CharacterString": "Num\u00e9rique"}}}}}, {"gfc:FC_FeatureAttribute": {"gfc:memberName": {"gco:LocalName": {"@xmlns:gco": "http://www.isotc211.org/2005/gco", "#text": "pos_sol"}}, "gfc:definition": {"gco:CharacterString": null}, "gfc:cardinality": {"gco:Multiplicity": {"@xmlns:gco": "http://www.isotc211.org/2005/gco", "gco:range": {"gco:MultiplicityRange": {"gco:lower": {"gco:Integer": "0"}, "gco:upper": {"gco:UnlimitedInteger": {"@xmlns:xsi": "http://www.w3.org/2001/XMLSchema-instance", "@isInfinite": "true", "@xsi:nil": "true"}}}}}}, "gfc:featureType": null, "gfc:valueMeasurementUnit": {"gml:UnitDefinition": {"@xmlns:gml": "http://www.opengis.net/gml", "@gml:id": null, "gml:identifier": {"@codeSpace": "unknown"}}}, "gfc:valueType": {"gco:TypeName": {"@xmlns:gco": "http://www.isotc211.org/2005/gco", "gco:aName": {"gco:CharacterString": "Num\u00e9rique"}}}}}, {"gfc:FC_FeatureAttribute": {"gfc:memberName": {"gco:LocalName": {"@xmlns:gco": "http://www.isotc211.org/2005/gco", "#text": "sens"}}, "gfc:definition": {"gco:CharacterString": null}, "gfc:cardinality": {"gco:Multiplicity": {"@xmlns:gco": "http://www.isotc211.org/2005/gco", "gco:range": {"gco:MultiplicityRange": {"gco:lower": {"gco:Integer": "0"}, "gco:upper": {"gco:UnlimitedInteger": {"@xmlns:xsi": "http://www.w3.org/2001/XMLSchema-instance", "@isInfinite": "true", "@xsi:nil": "true"}}}}}}, "gfc:featureType": null, "gfc:valueMeasurementUnit": {"gml:UnitDefinition": {"@xmlns:gml": "http://www.opengis.net/gml", "@gml:id": null, "gml:identifier": {"@codeSpace": "unknown"}}}, "gfc:valueType": {"gco:TypeName": {"@xmlns:gco": "http://www.isotc211.org/2005/gco", "gco:aName": {"gco:CharacterString": "Chaine de caract\u00e8res"}}}}}, {"gfc:FC_FeatureAttribute": {"gfc:memberName": {"gco:LocalName": {"@xmlns:gco": "http://www.isotc211.org/2005/gco", "#text": "inseecom_g"}}, "gfc:definition": {"gco:CharacterString": null}, "gfc:cardinality": {"gco:Multiplicity": {"@xmlns:gco": "http://www.isotc211.org/2005/gco", "gco:range": {"gco:MultiplicityRange": {"gco:lower": {"gco:Integer": "0"}, "gco:upper": {"gco:UnlimitedInteger": {"@xmlns:xsi": "http://www.w3.org/2001/XMLSchema-instance", "@isInfinite": "true", "@xsi:nil": "true"}}}}}}, "gfc:featureType": null, "gfc:valueMeasurementUnit": {"gml:UnitDefinition": {"@xmlns:gml": "http://www.opengis.net/gml", "@gml:id": null, "gml:identifier": {"@codeSpace": "unknown"}}}, "gfc:valueType": {"gco:TypeName": {"@xmlns:gco": "http://www.isotc211.org/2005/gco", "gco:aName": {"gco:CharacterString": "Chaine de caract\u00e8res"}}}}}, {"gfc:FC_FeatureAttribute": {"gfc:memberName": {"gco:LocalName": {"@xmlns:gco": "http://www.isotc211.org/2005/gco", "#text": "inseecom_d"}}, "gfc:definition": {"gco:CharacterString": null}, "gfc:cardinality": {"gco:Multiplicity": {"@xmlns:gco": "http://www.isotc211.org/2005/gco", "gco:range": {"gco:MultiplicityRange": {"gco:lower": {"gco:Integer": "0"}, "gco:upper": {"gco:UnlimitedInteger": {"@xmlns:xsi": "http://www.w3.org/2001/XMLSchema-instance", "@isInfinite": "true", "@xsi:nil": "true"}}}}}}, "gfc:featureType": null, "gfc:valueMeasurementUnit": {"gml:UnitDefinition": {"@xmlns:gml": "http://www.opengis.net/gml", "@gml:id": null, "gml:identifier": {"@codeSpace": "unknown"}}}, "gfc:valueType": {"gco:TypeName": {"@xmlns:gco": "http://www.isotc211.org/2005/gco", "gco:aName": {"gco:CharacterString": "Chaine de caract\u00e8res"}}}}}, {"gfc:FC_FeatureAttribute": {"gfc:memberName": {"gco:LocalName": {"@xmlns:gco": "http://www.isotc211.org/2005/gco", "#text": "codevoie_g"}}, "gfc:definition": {"gco:CharacterString": null}, "gfc:cardinality": {"gco:Multiplicity": {"@xmlns:gco": "http://www.isotc211.org/2005/gco", "gco:range": {"gco:MultiplicityRange": {"gco:lower": {"gco:Integer": "0"}, "gco:upper": {"gco:UnlimitedInteger": {"@xmlns:xsi": "http://www.w3.org/2001/XMLSchema-instance", "@isInfinite": "true", "@xsi:nil": "true"}}}}}}, "gfc:featureType": null, "gfc:valueMeasurementUnit": {"gml:UnitDefinition": {"@xmlns:gml": "http://www.opengis.net/gml", "@gml:id": null, "gml:identifier": {"@codeSpace": "unknown"}}}, "gfc:valueType": {"gco:TypeName": {"@xmlns:gco": "http://www.isotc211.org/2005/gco", "gco:aName": {"gco:CharacterString": "Chaine de caract\u00e8res"}}}}}, {"gfc:FC_FeatureAttribute": {"gfc:memberName": {"gco:LocalName": {"@xmlns:gco": "http://www.isotc211.org/2005/gco", "#text": "codevoie_d"}}, "gfc:definition": {"gco:CharacterString": null}, "gfc:cardinality": {"gco:Multiplicity": {"@xmlns:gco": "http://www.isotc211.org/2005/gco", "gco:range": {"gco:MultiplicityRange": {"gco:lower": {"gco:Integer": "0"}, "gco:upper": {"gco:UnlimitedInteger": {"@xmlns:xsi": "http://www.w3.org/2001/XMLSchema-instance", "@isInfinite": "true", "@xsi:nil": "true"}}}}}}, "gfc:featureType": null, "gfc:valueMeasurementUnit": {"gml:UnitDefinition": {"@xmlns:gml": "http://www.opengis.net/gml", "@gml:id": null, "gml:identifier": {"@codeSpace": "unknown"}}}, "gfc:valueType": {"gco:TypeName": {"@xmlns:gco": "http://www.isotc211.org/2005/gco", "gco:aName": {"gco:CharacterString": "Chaine de caract\u00e8res"}}}}}, {"gfc:FC_FeatureAttribute": {"gfc:memberName": {"gco:LocalName": {"@xmlns:gco": "http://www.isotc211.org/2005/gco", "#text": "typ_adres"}}, "gfc:definition": {"gco:CharacterString": null}, "gfc:cardinality": {"gco:Multiplicity": {"@xmlns:gco": "http://www.isotc211.org/2005/gco", "gco:range": {"gco:MultiplicityRange": {"gco:lower": {"gco:Integer": "0"}, "gco:upper": {"gco:UnlimitedInteger": {"@xmlns:xsi": "http://www.w3.org/2001/XMLSchema-instance", "@isInfinite": "true", "@xsi:nil": "true"}}}}}}, "gfc:featureType": null, "gfc:valueMeasurementUnit": {"gml:UnitDefinition": {"@xmlns:gml": "http://www.opengis.net/gml", "@gml:id": null, "gml:identifier": {"@codeSpace": "unknown"}}}, "gfc:valueType": {"gco:TypeName": {"@xmlns:gco": "http://www.isotc211.org/2005/gco", "gco:aName": {"gco:CharacterString": "Chaine de caract\u00e8res"}}}}}, {"gfc:FC_FeatureAttribute": {"gfc:memberName": {"gco:LocalName": {"@xmlns:gco": "http://www.isotc211.org/2005/gco", "#text": "bornedeb_g"}}, "gfc:definition": {"gco:CharacterString": null}, "gfc:cardinality": {"gco:Multiplicity": {"@xmlns:gco": "http://www.isotc211.org/2005/gco", "gco:range": {"gco:MultiplicityRange": {"gco:lower": {"gco:Integer": "0"}, "gco:upper": {"gco:UnlimitedInteger": {"@xmlns:xsi": "http://www.w3.org/2001/XMLSchema-instance", "@isInfinite": "true", "@xsi:nil": "true"}}}}}}, "gfc:featureType": null, "gfc:valueMeasurementUnit": {"gml:UnitDefinition": {"@xmlns:gml": "http://www.opengis.net/gml", "@gml:id": null, "gml:identifier": {"@codeSpace": "unknown"}}}, "gfc:valueType": {"gco:TypeName": {"@xmlns:gco": "http://www.isotc211.org/2005/gco", "gco:aName": {"gco:CharacterString": "Num\u00e9rique"}}}}}, {"gfc:FC_FeatureAttribute": {"gfc:memberName": {"gco:LocalName": {"@xmlns:gco": "http://www.isotc211.org/2005/gco", "#text": "bornedeb_d"}}, "gfc:definition": {"gco:CharacterString": null}, "gfc:cardinality": {"gco:Multiplicity": {"@xmlns:gco": "http://www.isotc211.org/2005/gco", "gco:range": {"gco:MultiplicityRange": {"gco:lower": {"gco:Integer": "0"}, "gco:upper": {"gco:UnlimitedInteger": {"@xmlns:xsi": "http://www.w3.org/2001/XMLSchema-instance", "@isInfinite": "true", "@xsi:nil": "true"}}}}}}, "gfc:featureType": null, "gfc:valueMeasurementUnit": {"gml:UnitDefinition": {"@xmlns:gml": "http://www.opengis.net/gml", "@gml:id": null, "gml:identifier": {"@codeSpace": "unknown"}}}, "gfc:valueType": {"gco:TypeName": {"@xmlns:gco": "http://www.isotc211.org/2005/gco", "gco:aName": {"gco:CharacterString": "Num\u00e9rique"}}}}}, {"gfc:FC_FeatureAttribute": {"gfc:memberName": {"gco:LocalName": {"@xmlns:gco": "http://www.isotc211.org/2005/gco", "#text": "bornefin_g"}}, "gfc:definition": {"gco:CharacterString": null}, "gfc:cardinality": {"gco:Multiplicity": {"@xmlns:gco": "http://www.isotc211.org/2005/gco", "gco:range": {"gco:MultiplicityRange": {"gco:lower": {"gco:Integer": "0"}, "gco:upper": {"gco:UnlimitedInteger": {"@xmlns:xsi": "http://www.w3.org/2001/XMLSchema-instance", "@isInfinite": "true", "@xsi:nil": "true"}}}}}}, "gfc:featureType": null, "gfc:valueMeasurementUnit": {"gml:UnitDefinition": {"@xmlns:gml": "http://www.opengis.net/gml", "@gml:id": null, "gml:identifier": {"@codeSpace": "unknown"}}}, "gfc:valueType": {"gco:TypeName": {"@xmlns:gco": "http://www.isotc211.org/2005/gco", "gco:aName": {"gco:CharacterString": "Num\u00e9rique"}}}}}, {"gfc:FC_FeatureAttribute": {"gfc:memberName": {"gco:LocalName": {"@xmlns:gco": "http://www.isotc211.org/2005/gco", "#text": "bornefin_d"}}, "gfc:definition": {"gco:CharacterString": null}, "gfc:cardinality": {"gco:Multiplicity": {"@xmlns:gco": "http://www.isotc211.org/2005/gco", "gco:range": {"gco:MultiplicityRange": {"gco:lower": {"gco:Integer": "0"}, "gco:upper": {"gco:UnlimitedInteger": {"@xmlns:xsi": "http://www.w3.org/2001/XMLSchema-instance", "@isInfinite": "true", "@xsi:nil": "true"}}}}}}, "gfc:featureType": null, "gfc:valueMeasurementUnit": {"gml:UnitDefinition": {"@xmlns:gml": "http://www.opengis.net/gml", "@gml:id": null, "gml:identifier": {"@codeSpace": "unknown"}}}, "gfc:valueType": {"gco:TypeName": {"@xmlns:gco": "http://www.isotc211.org/2005/gco", "gco:aName": {"gco:CharacterString": "Num\u00e9rique"}}}}}, {"gfc:FC_FeatureAttribute": {"gfc:memberName": {"gco:LocalName": {"@xmlns:gco": "http://www.isotc211.org/2005/gco", "#text": "etat"}}, "gfc:definition": {"gco:CharacterString": null}, "gfc:cardinality": {"gco:Multiplicity": {"@xmlns:gco": "http://www.isotc211.org/2005/gco", "gco:range": {"gco:MultiplicityRange": {"gco:lower": {"gco:Integer": "0"}, "gco:upper": {"gco:UnlimitedInteger": {"@xmlns:xsi": "http://www.w3.org/2001/XMLSchema-instance", "@isInfinite": "true", "@xsi:nil": "true"}}}}}}, "gfc:featureType": null, "gfc:valueMeasurementUnit": {"gml:UnitDefinition": {"@xmlns:gml": "http://www.opengis.net/gml", "@gml:id": null, "gml:identifier": {"@codeSpace": "unknown"}}}, "gfc:valueType": {"gco:TypeName": {"@xmlns:gco": "http://www.isotc211.org/2005/gco", "gco:aName": {"gco:CharacterString": "Chaine de caract\u00e8res"}}}}}, {"gfc:FC_FeatureAttribute": {"gfc:memberName": {"gco:LocalName": {"@xmlns:gco": "http://www.isotc211.org/2005/gco", "#text": "z_ini"}}, "gfc:definition": {"gco:CharacterString": null}, "gfc:cardinality": {"gco:Multiplicity": {"@xmlns:gco": "http://www.isotc211.org/2005/gco", "gco:range": {"gco:MultiplicityRange": {"gco:lower": {"gco:Integer": "0"}, "gco:upper": {"gco:UnlimitedInteger": {"@xmlns:xsi": "http://www.w3.org/2001/XMLSchema-instance", "@isInfinite": "true", "@xsi:nil": "true"}}}}}}, "gfc:featureType": null, "gfc:valueMeasurementUnit": {"gml:UnitDefinition": {"@xmlns:gml": "http://www.opengis.net/gml", "@gml:id": null, "gml:identifier": {"@codeSpace": "unknown"}}}, "gfc:valueType": {"gco:TypeName": {"@xmlns:gco": "http://www.isotc211.org/2005/gco", "gco:aName": {"gco:CharacterString": "Num\u00e9rique"}}}}}, {"gfc:FC_FeatureAttribute": {"gfc:memberName": {"gco:LocalName": {"@xmlns:gco": "http://www.isotc211.org/2005/gco", "#text": "z_fin"}}, "gfc:definition": {"gco:CharacterString": null}, "gfc:cardinality": {"gco:Multiplicity": {"@xmlns:gco": "http://www.isotc211.org/2005/gco", "gco:range": {"gco:MultiplicityRange": {"gco:lower": {"gco:Integer": "0"}, "gco:upper": {"gco:UnlimitedInteger": {"@xmlns:xsi": "http://www.w3.org/2001/XMLSchema-instance", "@isInfinite": "true", "@xsi:nil": "true"}}}}}}, "gfc:featureType": null, "gfc:valueMeasurementUnit": {"gml:UnitDefinition": {"@xmlns:gml": "http://www.opengis.net/gml", "@gml:id": null, "gml:identifier": {"@codeSpace": "unknown"}}}, "gfc:valueType": {"gco:TypeName": {"@xmlns:gco": "http://www.isotc211.org/2005/gco", "gco:aName": {"gco:CharacterString": "Num\u00e9rique"}}}}}]}}}