<?xml version="1.0" encoding="UTF-8"?>
<gmd:MD_Metadata xmlns:gmd="http://www.isotc211.org/2005/gmd"
                 xmlns:xsi="http://www.w3.org/2001/XMLSchema-instance"
                 xmlns:gco="http://www.isotc211.org/2005/gco"
                 xmlns:srv="http://www.isotc211.org/2005/srv"
                 xmlns:gmx="http://www.isotc211.org/2005/gmx"
                 xmlns:gts="http://www.isotc211.org/2005/gts"
                 xmlns:gsr="http://www.isotc211.org/2005/gsr"
                 xmlns:gmi="http://www.isotc211.org/2005/gmi"
                 xmlns:gml="http://www.opengis.net/gml/3.2"
                 xmlns:xlink="http://www.w3.org/1999/xlink"
                 xsi:schemaLocation="http://www.isotc211.org/2005/gmd http://schemas.opengis.net/csw/2.0.2/profiles/apiso/1.0.0/apiso.xsd">
  <gmd:fileIdentifier>
      <gco:CharacterString>89a5dc04-ec1a-4b84-98d2-c0095f0a82b4</gco:CharacterString>
  </gmd:fileIdentifier>
  <gmd:language xmlns:gml="http://www.opengis.net/gml" xmlns:gfc="http://www.isotc211.org/2005/gfc">
      <gco:CharacterString>eng</gco:CharacterString>
  </gmd:language>
  <gmd:characterSet xmlns:gml="http://www.opengis.net/gml" xmlns:gfc="http://www.isotc211.org/2005/gfc">
      <gmd:MD_CharacterSetCode codeListValue="utf8"
                               codeList="http://standards.iso.org/iso/19139/resources/gmxCodelists.xml#MD_CharacterSetCode"/>
  </gmd:characterSet>
  <gmd:hierarchyLevel xmlns:gml="http://www.opengis.net/gml" xmlns:gfc="http://www.isotc211.org/2005/gfc">
      <gmd:MD_ScopeCode codeListValue="dataset"
                        codeList="http://standards.iso.org/iso/19139/resources/gmxCodelists.xml#MD_ScopeCode"/>
  </gmd:hierarchyLevel>
  <gmd:hierarchyLevelName xmlns:gml="http://www.opengis.net/gml" xmlns:gfc="http://www.isotc211.org/2005/gfc">
      <gco:CharacterString>Série de données</gco:CharacterString>
  </gmd:hierarchyLevelName>
  <gmd:contact xmlns:gml="http://www.opengis.net/gml" xmlns:gfc="http://www.isotc211.org/2005/gfc">
      <gmd:CI_ResponsibleParty>
         <gmd:individualName>
            <gco:CharacterString>Florence, MAZIER</gco:CharacterString>
         </gmd:individualName>
         <gmd:organisationName>
            <gco:CharacterString>UMR 5602 - Géographie de l'environnement (GEODE)</gco:CharacterString>
         </gmd:organisationName>
         <gmd:contactInfo>
            <gmd:CI_Contact>
               <gmd:address>
                  <gmd:CI_Address>
                     <gmd:deliveryPoint>
                        <gco:CharacterString>5 allée Antonio Machado</gco:CharacterString>
                     </gmd:deliveryPoint>
                     <gmd:city>
                        <gco:CharacterString>TOULOUSE</gco:CharacterString>
                     </gmd:city>
                     <gmd:postalCode>
                        <gco:CharacterString>31058</gco:CharacterString>
                     </gmd:postalCode>
                     <gmd:country>
                        <gco:CharacterString>France</gco:CharacterString>
                     </gmd:country>
                     <gmd:electronicMailAddress>
                        <gco:CharacterString>florence.mazier@univ-tlse2.fr</gco:CharacterString>
                     </gmd:electronicMailAddress>
                  </gmd:CI_Address>
               </gmd:address>
            </gmd:CI_Contact>
         </gmd:contactInfo>
         <gmd:role>
            <gmd:CI_RoleCode codeList="http://standards.iso.org/iso/19139/resources/gmxCodelists.xml#CI_RoleCode"
                             codeListValue="pointOfContact"/>
         </gmd:role>
      </gmd:CI_ResponsibleParty>
  </gmd:contact>
  <gmd:dateStamp xmlns:gml="http://www.opengis.net/gml" xmlns:gfc="http://www.isotc211.org/2005/gfc">
      <gco:DateTime>2023-06-09T09:58:18.181Z</gco:DateTime>
  </gmd:dateStamp>
  <gmd:metadataStandardName xmlns:gml="http://www.opengis.net/gml" xmlns:gfc="http://www.isotc211.org/2005/gfc">
      <gco:CharacterString>ISO 19115:2003/19139</gco:CharacterString>
  </gmd:metadataStandardName>
  <gmd:metadataStandardVersion xmlns:gml="http://www.opengis.net/gml" xmlns:gfc="http://www.isotc211.org/2005/gfc">
      <gco:CharacterString>1.0</gco:CharacterString>
  </gmd:metadataStandardVersion>
  <gmd:referenceSystemInfo xmlns:gml="http://www.opengis.net/gml" xmlns:gfc="http://www.isotc211.org/2005/gfc">
      <gmd:MD_ReferenceSystem>
         <gmd:referenceSystemIdentifier/>
      </gmd:MD_ReferenceSystem>
  </gmd:referenceSystemInfo>
  <gmd:identificationInfo xmlns:gml="http://www.opengis.net/gml" xmlns:gfc="http://www.isotc211.org/2005/gfc">
      <gmd:MD_DataIdentification>
         <gmd:citation>
            <gmd:CI_Citation>
               <gmd:title>
                  <gco:CharacterString>Vegetation surveys in mountainous area (Pyrenees, France)</gco:CharacterString>
               </gmd:title>
               <gmd:date>
                  <gmd:CI_Date>
                     <gmd:date>
                        <gco:Date>2022-09-15</gco:Date>
                     </gmd:date>
                     <gmd:dateType>
                        <gmd:CI_DateTypeCode codeListValue="publication"
                                             codeList="http://standards.iso.org/iso/19139/resources/gmxCodelists.xml#CI_DateTypeCode"/>
                     </gmd:dateType>
                  </gmd:CI_Date>
               </gmd:date>
               <gmd:identifier>
                  <gmd:MD_Identifier>
                     <gmd:code>
                        <gco:CharacterString>https://doi.org/10.48579/PRO/9SI1PN</gco:CharacterString>
                     </gmd:code>
                  </gmd:MD_Identifier>
               </gmd:identifier>
               <gmd:identifier>
                  <gmd:MD_Identifier>
                     <gmd:code>
                        <gco:CharacterString>https://geo.driihm.fr/geonetwork/ohm-hv/fre/catalog.search#/metadata/89a5dc04-ec1a-4b84-98d2-c0095f0a82b4</gco:CharacterString>
                     </gmd:code>
                  </gmd:MD_Identifier>
               </gmd:identifier>
               <gmd:citedResponsibleParty>
                  <gmd:CI_ResponsibleParty>
                     <gmd:individualName>
                        <gco:CharacterString>Florence, MAZIER</gco:CharacterString>
                     </gmd:individualName>
                     <gmd:organisationName>
                        <gco:CharacterString>UMR 5602 - Géographie de l'environnement (GEODE)</gco:CharacterString>
                     </gmd:organisationName>
                     <gmd:contactInfo>
                        <gmd:CI_Contact>
                           <gmd:address>
                              <gmd:CI_Address>
                                 <gmd:deliveryPoint>
                                    <gco:CharacterString>5 allée Antonio Machado</gco:CharacterString>
                                 </gmd:deliveryPoint>
                                 <gmd:city>
                                    <gco:CharacterString>TOULOUSE</gco:CharacterString>
                                 </gmd:city>
                                 <gmd:postalCode>
                                    <gco:CharacterString>31058</gco:CharacterString>
                                 </gmd:postalCode>
                                 <gmd:electronicMailAddress>
                                    <gco:CharacterString>florence.mazier@univ-tlse2.fr</gco:CharacterString>
                                 </gmd:electronicMailAddress>
                              </gmd:CI_Address>
                           </gmd:address>
                        </gmd:CI_Contact>
                     </gmd:contactInfo>
                     <gmd:role>
                        <gmd:CI_RoleCode codeList="http://standards.iso.org/iso/19139/resources/gmxCodelists.xml#CI_RoleCode"
                                         codeListValue="author"/>
                     </gmd:role>
                  </gmd:CI_ResponsibleParty>
               </gmd:citedResponsibleParty>
            </gmd:CI_Citation>
         </gmd:citation>
         <gmd:abstract>
            <gco:CharacterString>The data file contains absolute cover percentage of plant species from vegetation survey in the Vicdessos mountainous area (Pyrenees, France). The data have been collected in 2015 and 2020 within the framework of two projects: ANR-10-JCJC-1804 MODE-RESPYR (Modeling Past and future land cover changes in the Pyrenees) and the PASTSERV project funded by the Observatoire Hommes-Milieux Pyrenees Haut Vicdessos (Labex DRIIHM ANR-11-LABX0010). All observed vascular plant species were listed and the cover of each species was estimated using the seven degrees of the Braun-Blanquet scale (r, +, 1, 2, 3, 4, 5). These codes were then converted to absolute percentage cover (van der Maarel 1979). 
The version of the data file formatted according to the Darwin Core standard has been uploaded to GBIF (https://doi.org/10.15468/4q47d3). 
The original raw data file is accessible in the CNRS-INEE data.indores repository https://doi.org/10.48579/PRO/9SI1PN.</gco:CharacterString>
         </gmd:abstract>
         <gmd:pointOfContact>
            <gmd:CI_ResponsibleParty>
               <gmd:individualName>
                  <gco:CharacterString>Florence, MAZIER</gco:CharacterString>
               </gmd:individualName>
               <gmd:organisationName>
                  <gco:CharacterString>UMR 5602 - Géographie de l'environnement (GEODE)</gco:CharacterString>
               </gmd:organisationName>
               <gmd:contactInfo>
                  <gmd:CI_Contact>
                     <gmd:address>
                        <gmd:CI_Address>
                           <gmd:city>
                              <gco:CharacterString>TOULOUSE</gco:CharacterString>
                           </gmd:city>
                           <gmd:postalCode>
                              <gco:CharacterString>31058</gco:CharacterString>
                           </gmd:postalCode>
                           <gmd:country>
                              <gco:CharacterString>France</gco:CharacterString>
                           </gmd:country>
                           <gmd:electronicMailAddress>
                              <gco:CharacterString>florence.mazier@univ-tlse2.fr</gco:CharacterString>
                           </gmd:electronicMailAddress>
                        </gmd:CI_Address>
                     </gmd:address>
                  </gmd:CI_Contact>
               </gmd:contactInfo>
               <gmd:role>
                  <gmd:CI_RoleCode codeList="http://standards.iso.org/iso/19139/resources/gmxCodelists.xml#CI_RoleCode"
                                   codeListValue="pointOfContact"/>
               </gmd:role>
            </gmd:CI_ResponsibleParty>
         </gmd:pointOfContact>
         <gmd:graphicOverview>
            <gmd:MD_BrowseGraphic>
               <gmd:fileName>
                  <gco:CharacterString>https://cat.indores.fr/geonetwork/srv/api/records/89a5dc04-ec1a-4b84-98d2-c0095f0a82b4/attachments/89a5dc04-ec1a-4b84-98d2-c0095f0a82b4.png</gco:CharacterString>
               </gmd:fileName>
            </gmd:MD_BrowseGraphic>
         </gmd:graphicOverview>
         <gmd:descriptiveKeywords>
            <gmd:MD_Keywords>
               <gmd:keyword>
                  <gco:CharacterString>mountainous area</gco:CharacterString>
               </gmd:keyword>
               <gmd:keyword>
                  <gco:CharacterString>biodiversity</gco:CharacterString>
               </gmd:keyword>
               <gmd:keyword>
                  <gco:CharacterString>plant community</gco:CharacterString>
               </gmd:keyword>
               <gmd:keyword>
                  <gco:CharacterString>OHM Pyrénées Haut Vicdessos</gco:CharacterString>
               </gmd:keyword>
            </gmd:MD_Keywords>
         </gmd:descriptiveKeywords>
         <gmd:descriptiveKeywords>
            <gmd:MD_Keywords>
               <gmd:keyword gco:nilReason="missing">
                  <gco:CharacterString/>
               </gmd:keyword>
               <gmd:type>
                  <gmd:MD_KeywordTypeCode codeList="http://standards.iso.org/iso/19139/resources/gmxCodelists.xml#MD_KeywordTypeCode"
                                          codeListValue="place"/>
               </gmd:type>
               <gmd:thesaurusName>
                  <gmd:CI_Citation>
                     <gmd:title>
                        <gco:CharacterString>Continents, countries, sea regions of the world.</gco:CharacterString>
                     </gmd:title>
                     <gmd:date>
                        <gmd:CI_Date>
                           <gmd:date>
                              <gco:Date>2015-07-17 12:00:00</gco:Date>
                           </gmd:date>
                           <gmd:dateType>
                              <gmd:CI_DateTypeCode codeList="http://standards.iso.org/iso/19139/resources/gmxCodelists.xml#CI_DateTypeCode"
                                                   codeListValue="publication"/>
                           </gmd:dateType>
                        </gmd:CI_Date>
                     </gmd:date>
                     <gmd:identifier>
                        <gmd:MD_Identifier>
                           <gmd:code>
                              <gmx:Anchor xlink:href="https://geo.driihm.fr/geonetwork/srv/api/registries/vocabularies/external.place.regions">geonetwork.thesaurus.external.place.regions</gmx:Anchor>
                           </gmd:code>
                        </gmd:MD_Identifier>
                     </gmd:identifier>
                  </gmd:CI_Citation>
               </gmd:thesaurusName>
            </gmd:MD_Keywords>
         </gmd:descriptiveKeywords>
         <gmd:resourceConstraints>
            <gmd:MD_Constraints>
               <gmd:useLimitation>
                  <gco:CharacterString>Données ouvertes</gco:CharacterString>
               </gmd:useLimitation>
            </gmd:MD_Constraints>
         </gmd:resourceConstraints>
         <gmd:resourceConstraints>
            <gmd:MD_LegalConstraints>
               <gmd:accessConstraints>
                  <gmd:MD_RestrictionCode codeList="http://standards.iso.org/iso/19139/resources/gmxCodelists.xml#MD_RestrictionCode"
                                          codeListValue="license"/>
               </gmd:accessConstraints>
            </gmd:MD_LegalConstraints>
         </gmd:resourceConstraints>
         <gmd:resourceConstraints>
            <gmd:MD_SecurityConstraints>
               <gmd:classification>
                  <gmd:MD_ClassificationCode codeList="http://standards.iso.org/iso/19139/resources/gmxCodelists.xml#MD_ClassificationCode"
                                             codeListValue="unclassified"/>
               </gmd:classification>
               <gmd:userNote gco:nilReason="missing">
                  <gco:CharacterString/>
               </gmd:userNote>
            </gmd:MD_SecurityConstraints>
         </gmd:resourceConstraints>
         <gmd:language>
            <gco:CharacterString>eng</gco:CharacterString>
         </gmd:language>
         <gmd:characterSet>
            <gmd:MD_CharacterSetCode codeListValue="utf8"
                                     codeList="http://standards.iso.org/iso/19139/resources/gmxCodelists.xml#MD_CharacterSetCode"/>
         </gmd:characterSet>
         <gmd:topicCategory>
            <gmd:MD_TopicCategoryCode>biota</gmd:MD_TopicCategoryCode>
         </gmd:topicCategory>
         <gmd:extent>
            <gmd:EX_Extent>
               <gmd:geographicElement>
                  <gmd:EX_GeographicBoundingBox>
                     <gmd:westBoundLongitude>
                        <gco:Decimal>1.349</gco:Decimal>
                     </gmd:westBoundLongitude>
                     <gmd:eastBoundLongitude>
                        <gco:Decimal>1.475</gco:Decimal>
                     </gmd:eastBoundLongitude>
                     <gmd:southBoundLatitude>
                        <gco:Decimal>42.74</gco:Decimal>
                     </gmd:southBoundLatitude>
                     <gmd:northBoundLatitude>
                        <gco:Decimal>42.806</gco:Decimal>
                     </gmd:northBoundLatitude>
                  </gmd:EX_GeographicBoundingBox>
               </gmd:geographicElement>
               <gmd:temporalElement/>
               <gmd:verticalElement/>
            </gmd:EX_Extent>
         </gmd:extent>
      </gmd:MD_DataIdentification>
  </gmd:identificationInfo>
  <gmd:distributionInfo>
      <gmd:MD_Distribution>
         <gmd:distributionFormat xmlns:gml="http://www.opengis.net/gml" xmlns:gfc="http://www.isotc211.org/2005/gfc"
                                 xmlns:date="http://exslt.org/dates-and-times">
            <gmd:MD_Format>
               <gmd:name>
                  <gco:CharacterString>ODS</gco:CharacterString>
               </gmd:name>
               <gmd:version gco:nilReason="unknown">
                  <gco:CharacterString/>
               </gmd:version>
               <gmd:formatDistributor>
                  <gmd:MD_Distributor>
                     <gmd:distributorContact>
                        <gmd:CI_ResponsibleParty>
                           <gmd:organisationName gco:nilReason="missing">
                              <gco:CharacterString/>
                           </gmd:organisationName>
                           <gmd:contactInfo>
                              <gmd:CI_Contact>
                                 <gmd:address>
                                    <gmd:CI_Address>
                                       <gmd:electronicMailAddress gco:nilReason="missing">
                                          <gco:CharacterString/>
                                       </gmd:electronicMailAddress>
                                    </gmd:CI_Address>
                                 </gmd:address>
                              </gmd:CI_Contact>
                           </gmd:contactInfo>
                           <gmd:role>
                              <gmd:CI_RoleCode codeList="http://standards.iso.org/iso/19139/resources/gmxCodelists.xml#CI_RoleCode"
                                               codeListValue=""/>
                           </gmd:role>
                        </gmd:CI_ResponsibleParty>
                     </gmd:distributorContact>
                  </gmd:MD_Distributor>
               </gmd:formatDistributor>
            </gmd:MD_Format>
         </gmd:distributionFormat>
         <gmd:distributor xmlns:gml="http://www.opengis.net/gml" xmlns:gfc="http://www.isotc211.org/2005/gfc"
                          xmlns:date="http://exslt.org/dates-and-times">
            <gmd:MD_Distributor>
               <gmd:distributorContact>
                  <gmd:CI_ResponsibleParty>
                     <gmd:individualName gco:nilReason="missing">
                        <gco:CharacterString/>
                     </gmd:individualName>
                     <gmd:organisationName>
                        <gco:CharacterString>GBIF</gco:CharacterString>
                     </gmd:organisationName>
                     <gmd:contactInfo>
                        <gmd:CI_Contact>
                           <gmd:address>
                              <gmd:CI_Address>
                                 <gmd:electronicMailAddress gco:nilReason="missing">
                                    <gco:CharacterString/>
                                 </gmd:electronicMailAddress>
                              </gmd:CI_Address>
                           </gmd:address>
                        </gmd:CI_Contact>
                     </gmd:contactInfo>
                     <gmd:role>
                        <gmd:CI_RoleCode codeList="http://standards.iso.org/iso/19139/resources/gmxCodelists.xml#CI_RoleCode"
                                         codeListValue=""/>
                     </gmd:role>
                  </gmd:CI_ResponsibleParty>
               </gmd:distributorContact>
            </gmd:MD_Distributor>
         </gmd:distributor>
         <gmd:distributor>
            <gmd:MD_Distributor>
               <gmd:distributorContact>
                  <gmd:CI_ResponsibleParty>
                     <gmd:individualName gco:nilReason="missing">
                        <gco:CharacterString/>
                     </gmd:individualName>
                     <gmd:organisationName>
                        <gco:CharacterString>DATA.INDORES</gco:CharacterString>
                     </gmd:organisationName>
                     <gmd:contactInfo>
                        <gmd:CI_Contact>
                           <gmd:address>
                              <gmd:CI_Address>
                                 <gmd:electronicMailAddress gco:nilReason="missing">
                                    <gco:CharacterString/>
                                 </gmd:electronicMailAddress>
                              </gmd:CI_Address>
                           </gmd:address>
                        </gmd:CI_Contact>
                     </gmd:contactInfo>
                     <gmd:role>
                        <gmd:CI_RoleCode codeList="http://standards.iso.org/iso/19139/resources/gmxCodelists.xml#CI_RoleCode"
                                         codeListValue=""/>
                     </gmd:role>
                  </gmd:CI_ResponsibleParty>
               </gmd:distributorContact>
            </gmd:MD_Distributor>
         </gmd:distributor>
         <gmd:transferOptions>
            <gmd:MD_DigitalTransferOptions>
               <gmd:onLine xmlns:gml="http://www.opengis.net/gml" xmlns:gfc="http://www.isotc211.org/2005/gfc"
                           xmlns:date="http://exslt.org/dates-and-times">
                  <gmd:CI_OnlineResource>
                     <gmd:linkage>
                        <gmd:URL>https://www.driihm.fr/projets/projets-2020/details/149/2266</gmd:URL>
                     </gmd:linkage>
                     <gmd:name>
                        <gco:CharacterString>Projet OHM PASTSERV 2020</gco:CharacterString>
                     </gmd:name>
                  </gmd:CI_OnlineResource>
               </gmd:onLine>
               <gmd:onLine>
                  <gmd:CI_OnlineResource>
                     <gmd:linkage>
                        <gmd:URL>https://data.indores.fr/dataset.xhtml?persistentId=doi:10.48579/PRO/9SI1PN</gmd:URL>
                     </gmd:linkage>
                     <gmd:protocol>
                        <gco:CharacterString>WWW:LINK-1.0-http--link</gco:CharacterString>
                     </gmd:protocol>
                     <gmd:name>
                        <gco:CharacterString>Source file on data.indores.fr</gco:CharacterString>
                     </gmd:name>
                     <gmd:description>
                        <gco:CharacterString>This file is the original raw data file</gco:CharacterString>
                     </gmd:description>
                     <gmd:function>
                        <gmd:CI_OnLineFunctionCode codeList="http://standards.iso.org/iso/19139/resources/gmxCodelists.xml#CI_OnLineFunctionCode"
                                                   codeListValue="download"/>
                     </gmd:function>
                  </gmd:CI_OnlineResource>
               </gmd:onLine>
               <gmd:onLine>
                  <gmd:CI_OnlineResource>
                     <gmd:linkage>
                        <gmd:URL>https://www.gbif.org/dataset/25b73b90-475a-4a8c-954a-1a5cb8f8b2e9</gmd:URL>
                     </gmd:linkage>
                     <gmd:protocol>
                        <gco:CharacterString>null</gco:CharacterString>
                     </gmd:protocol>
                     <gmd:name>
                        <gco:CharacterString>File based on Darwin core standard published on GBIF website</gco:CharacterString>
                     </gmd:name>
                     <gmd:description>
                        <gco:CharacterString>The source file was transformed using the Darwin core standard elements in order to be published on GBIF</gco:CharacterString>
                     </gmd:description>
                     <gmd:function>
                        <gmd:CI_OnLineFunctionCode codeList="http://standards.iso.org/iso/19139/resources/gmxCodelists.xml#CI_OnLineFunctionCode"
                                                   codeListValue="download"/>
                     </gmd:function>
                  </gmd:CI_OnlineResource>
               </gmd:onLine>
            </gmd:MD_DigitalTransferOptions>
         </gmd:transferOptions>
         <gmd:transferOptions xmlns:gml="http://www.opengis.net/gml" xmlns:gfc="http://www.isotc211.org/2005/gfc"
                              xmlns:date="http://exslt.org/dates-and-times">
            <gmd:MD_DigitalTransferOptions/>
         </gmd:transferOptions>
      </gmd:MD_Distribution>
  </gmd:distributionInfo>
  <gmd:dataQualityInfo xmlns:gml="http://www.opengis.net/gml" xmlns:gfc="http://www.isotc211.org/2005/gfc">
      <gmd:DQ_DataQuality>
         <gmd:scope>
            <gmd:DQ_Scope>
               <gmd:level>
                  <gmd:MD_ScopeCode codeList="http://standards.iso.org/iso/19139/resources/gmxCodelists.xml#MD_ScopeCode"
                                    codeListValue="dataset"/>
               </gmd:level>
               <gmd:extent>
                  <gmd:EX_Extent>
                     <gmd:temporalElement/>
                     <gmd:temporalElement/>
                  </gmd:EX_Extent>
               </gmd:extent>
            </gmd:DQ_Scope>
         </gmd:scope>
      </gmd:DQ_DataQuality>
  </gmd:dataQualityInfo>
  <gmd:metadataConstraints xmlns:gml="http://www.opengis.net/gml" xmlns:gfc="http://www.isotc211.org/2005/gfc">
      <gmd:MD_SecurityConstraints>
         <gmd:classification>
            <gmd:MD_ClassificationCode codeList="http://standards.iso.org/iso/19139/resources/gmxCodelists.xml#MD_ClassificationCode"
                                       codeListValue=""/>
         </gmd:classification>
      </gmd:MD_SecurityConstraints>
  </gmd:metadataConstraints>
</gmd:MD_Metadata>