<?xml version="1.0" encoding="UTF-8"?>
<gmd:MD_Metadata xmlns:gmd="http://www.isotc211.org/2005/gmd"
                 xmlns:xsi="http://www.w3.org/2001/XMLSchema-instance"
                 xmlns:gco="http://www.isotc211.org/2005/gco"
                 xmlns:srv="http://www.isotc211.org/2005/srv"
                 xmlns:gmx="http://www.isotc211.org/2005/gmx"
                 xmlns:gts="http://www.isotc211.org/2005/gts"
                 xmlns:gsr="http://www.isotc211.org/2005/gsr"
                 xmlns:gmi="http://www.isotc211.org/2005/gmi"
                 xmlns:gml="http://www.opengis.net/gml/3.2"
                 xmlns:xlink="http://www.w3.org/1999/xlink"
                 xsi:schemaLocation="http://www.isotc211.org/2005/gmd http://schemas.opengis.net/csw/2.0.2/profiles/apiso/1.0.0/apiso.xsd">
  <gmd:fileIdentifier>
      <gco:CharacterString>a0f7e3d3-25fd-4aba-b4c1-21618dc70eab</gco:CharacterString>
  </gmd:fileIdentifier>
  <gmd:language xmlns:gml="http://www.opengis.net/gml">
      <gco:CharacterString>fre</gco:CharacterString>
  </gmd:language>
  <gmd:characterSet xmlns:gml="http://www.opengis.net/gml">
      <gmd:MD_CharacterSetCode codeListValue="utf8"
                               codeList="http://standards.iso.org/iso/19139/resources/gmxCodelists.xml#MD_CharacterSetCode"/>
  </gmd:characterSet>
  <gmd:hierarchyLevel xmlns:gml="http://www.opengis.net/gml">
      <gmd:MD_ScopeCode codeList="http://standards.iso.org/iso/19139/resources/gmxCodelists.xml#MD_ScopeCode"
                        codeListValue="dataset"/>
  </gmd:hierarchyLevel>
  <gmd:hierarchyLevelName xmlns:gml="http://www.opengis.net/gml">
      <gco:CharacterString>Série de données</gco:CharacterString>
  </gmd:hierarchyLevelName>
  <gmd:contact xmlns:gml="http://www.opengis.net/gml">
      <gmd:CI_ResponsibleParty>
         <gmd:individualName>
            <gco:CharacterString>Thomas, HOUET</gco:CharacterString>
         </gmd:individualName>
         <gmd:organisationName>
            <gco:CharacterString>UMR 5602 - Géographie de l'Environnement (GEODE)</gco:CharacterString>
         </gmd:organisationName>
         <gmd:positionName>
            <gco:CharacterString>Chargé de recherche CNRS</gco:CharacterString>
         </gmd:positionName>
         <gmd:contactInfo>
            <gmd:CI_Contact>
               <gmd:phone>
                  <gmd:CI_Telephone>
                     <gmd:voice>
                        <gco:CharacterString>0561503628</gco:CharacterString>
                     </gmd:voice>
                     <gmd:facsimile gco:nilReason="missing">
                        <gco:CharacterString/>
                     </gmd:facsimile>
                  </gmd:CI_Telephone>
               </gmd:phone>
               <gmd:address>
                  <gmd:CI_Address>
                     <gmd:deliveryPoint>
                        <gco:CharacterString>5 Allées Antonio Machado</gco:CharacterString>
                     </gmd:deliveryPoint>
                     <gmd:city>
                        <gco:CharacterString>TOULOUSE</gco:CharacterString>
                     </gmd:city>
                     <gmd:administrativeArea gco:nilReason="missing">
                        <gco:CharacterString/>
                     </gmd:administrativeArea>
                     <gmd:postalCode>
                        <gco:CharacterString>31058</gco:CharacterString>
                     </gmd:postalCode>
                     <gmd:country>
                        <gco:CharacterString>France</gco:CharacterString>
                     </gmd:country>
                     <gmd:electronicMailAddress>
                        <gco:CharacterString>thomas.houet@univ-tlse2.fr</gco:CharacterString>
                     </gmd:electronicMailAddress>
                  </gmd:CI_Address>
               </gmd:address>
            </gmd:CI_Contact>
         </gmd:contactInfo>
         <gmd:role>
            <gmd:CI_RoleCode codeListValue="pointOfContact"
                             codeList="http://standards.iso.org/iso/19139/resources/gmxCodelists.xml#CI_RoleCode"/>
         </gmd:role>
      </gmd:CI_ResponsibleParty>
  </gmd:contact>
  <gmd:dateStamp xmlns:gml="http://www.opengis.net/gml">
      <gco:DateTime>2023-06-09T10:02:19.927Z</gco:DateTime>
  </gmd:dateStamp>
  <gmd:metadataStandardName xmlns:gml="http://www.opengis.net/gml">
      <gco:CharacterString>ISO 19115:2003/19139</gco:CharacterString>
  </gmd:metadataStandardName>
  <gmd:metadataStandardVersion xmlns:gml="http://www.opengis.net/gml">
      <gco:CharacterString>1.0</gco:CharacterString>
  </gmd:metadataStandardVersion>
  <gmd:referenceSystemInfo xmlns:gml="http://www.opengis.net/gml">
      <gmd:MD_ReferenceSystem>
         <gmd:referenceSystemIdentifier>
            <gmd:RS_Identifier>
               <gmd:code>
                  <gco:CharacterString>NTF (Paris) / Lambert zone II (EPSG:27572)</gco:CharacterString>
               </gmd:code>
               <gmd:codeSpace>
                  <gco:CharacterString>EPSG</gco:CharacterString>
               </gmd:codeSpace>
               <gmd:version>
                  <gco:CharacterString>7.4</gco:CharacterString>
               </gmd:version>
            </gmd:RS_Identifier>
         </gmd:referenceSystemIdentifier>
      </gmd:MD_ReferenceSystem>
  </gmd:referenceSystemInfo>
  <gmd:identificationInfo xmlns:gml="http://www.opengis.net/gml">
      <gmd:MD_DataIdentification>
         <gmd:citation>
            <gmd:CI_Citation>
               <gmd:title>
                  <gco:CharacterString>Cartographie des zones humides de Bassiès</gco:CharacterString>
               </gmd:title>
               <gmd:date>
                  <gmd:CI_Date>
                     <gmd:date>
                        <gco:DateTime>2010-07-01T01:00:00</gco:DateTime>
                     </gmd:date>
                     <gmd:dateType>
                        <gmd:CI_DateTypeCode codeListValue="publication"
                                             codeList="http://standards.iso.org/iso/19139/resources/gmxCodelists.xml#CI_DateTypeCode"/>
                     </gmd:dateType>
                  </gmd:CI_Date>
               </gmd:date>
               <gmd:edition gco:nilReason="missing">
                  <gco:CharacterString/>
               </gmd:edition>
               <gmd:identifier>
                  <gmd:MD_Identifier>
                     <gmd:code>
                        <gco:CharacterString>https://geo.driihm.fr/geonetwork/ohm-hv/fre/catalog.search#/metadata/a0f7e3d3-25fd-4aba-b4c1-21618dc70eab</gco:CharacterString>
                     </gmd:code>
                  </gmd:MD_Identifier>
               </gmd:identifier>
               <gmd:presentationForm>
                  <gmd:CI_PresentationFormCode codeListValue="mapDigital"
                                               codeList="http://standards.iso.org/iso/19139/resources/gmxCodelists.xml#CI_PresentationFormCode"/>
               </gmd:presentationForm>
            </gmd:CI_Citation>
         </gmd:citation>
         <gmd:abstract>
            <gco:CharacterString>Cartographie des zones humides issue de relevés in situ réalisés en 2010, servant de données de validation des classifications pour les cartes d'occupation des sols.
Ref : Vacquié L. et Houet T. (2012) Détection et caractérisation des zones humides de montagnes par télédétection: évaluation de l’apport de la Très Haute Résolution Spatiale. Revue Internationale de Géomatique, Vol. 22, 2012/4, 497-518</gco:CharacterString>
         </gmd:abstract>
         <gmd:purpose>
            <gco:CharacterString>Créer une base de données référençant le nombre et la nature des zones humides de Bassiès en 2010</gco:CharacterString>
         </gmd:purpose>
         <gmd:status>
            <gmd:MD_ProgressCode codeListValue="completed"
                                 codeList="http://standards.iso.org/iso/19139/resources/gmxCodelists.xml#MD_ProgressCode"/>
         </gmd:status>
         <gmd:pointOfContact>
            <gmd:CI_ResponsibleParty>
               <gmd:individualName>
                  <gco:CharacterString>Thomas, HOUET</gco:CharacterString>
               </gmd:individualName>
               <gmd:organisationName>
                  <gco:CharacterString>UMR 5602 - Géographie de l'Environnement (GEODE)</gco:CharacterString>
               </gmd:organisationName>
               <gmd:positionName>
                  <gco:CharacterString>Chargé de recherche CNRS</gco:CharacterString>
               </gmd:positionName>
               <gmd:contactInfo>
                  <gmd:CI_Contact>
                     <gmd:phone>
                        <gmd:CI_Telephone>
                           <gmd:voice>
                              <gco:CharacterString>0561503628</gco:CharacterString>
                           </gmd:voice>
                           <gmd:facsimile gco:nilReason="missing">
                              <gco:CharacterString/>
                           </gmd:facsimile>
                        </gmd:CI_Telephone>
                     </gmd:phone>
                     <gmd:address>
                        <gmd:CI_Address>
                           <gmd:deliveryPoint>
                              <gco:CharacterString>5 Allées Antonio Machado</gco:CharacterString>
                           </gmd:deliveryPoint>
                           <gmd:city>
                              <gco:CharacterString>TOULOUSE</gco:CharacterString>
                           </gmd:city>
                           <gmd:administrativeArea gco:nilReason="missing">
                              <gco:CharacterString/>
                           </gmd:administrativeArea>
                           <gmd:postalCode>
                              <gco:CharacterString>31058</gco:CharacterString>
                           </gmd:postalCode>
                           <gmd:country>
                              <gco:CharacterString>France</gco:CharacterString>
                           </gmd:country>
                           <gmd:electronicMailAddress>
                              <gco:CharacterString>thomas.houet@univ-tlse2.fr</gco:CharacterString>
                           </gmd:electronicMailAddress>
                        </gmd:CI_Address>
                     </gmd:address>
                  </gmd:CI_Contact>
               </gmd:contactInfo>
               <gmd:role>
                  <gmd:CI_RoleCode codeListValue="pointOfContact"
                                   codeList="http://standards.iso.org/iso/19139/resources/gmxCodelists.xml#CI_RoleCode"/>
               </gmd:role>
            </gmd:CI_ResponsibleParty>
         </gmd:pointOfContact>
         <gmd:resourceMaintenance>
            <gmd:MD_MaintenanceInformation>
               <gmd:maintenanceAndUpdateFrequency>
                  <gmd:MD_MaintenanceFrequencyCode codeListValue="asNeeded"
                                                   codeList="http://standards.iso.org/iso/19139/resources/gmxCodelists.xml#MD_MaintenanceFrequencyCode"/>
               </gmd:maintenanceAndUpdateFrequency>
            </gmd:MD_MaintenanceInformation>
         </gmd:resourceMaintenance>
         <gmd:graphicOverview>
            <gmd:MD_BrowseGraphic>
               <gmd:fileName>
                  <gco:CharacterString>https://cat.indores.fr/geonetwork/srv/api/records/a0f7e3d3-25fd-4aba-b4c1-21618dc70eab/attachments/zones_humides_bassies_800px.png</gco:CharacterString>
               </gmd:fileName>
               <gmd:fileDescription>
                  <gco:CharacterString>large_thumbnail</gco:CharacterString>
               </gmd:fileDescription>
               <gmd:fileType>
                  <gco:CharacterString>png</gco:CharacterString>
               </gmd:fileType>
            </gmd:MD_BrowseGraphic>
         </gmd:graphicOverview>
         <gmd:descriptiveKeywords>
            <gmd:MD_Keywords>
               <gmd:keyword>
                  <gco:CharacterString>zones humides</gco:CharacterString>
               </gmd:keyword>
               <gmd:keyword>
                  <gco:CharacterString>cartographie</gco:CharacterString>
               </gmd:keyword>
               <gmd:keyword>
                  <gco:CharacterString>OHM Pyrénées Haut Vicdessos</gco:CharacterString>
               </gmd:keyword>
            </gmd:MD_Keywords>
         </gmd:descriptiveKeywords>
         <gmd:resourceConstraints>
            <gmd:MD_LegalConstraints>
               <gmd:accessConstraints>
                  <gmd:MD_RestrictionCode codeListValue="copyright"
                                          codeList="http://standards.iso.org/iso/19139/resources/gmxCodelists.xml#MD_RestrictionCode"/>
               </gmd:accessConstraints>
               <gmd:useConstraints>
                  <gmd:MD_RestrictionCode codeListValue=""
                                          codeList="http://standards.iso.org/iso/19139/resources/gmxCodelists.xml#MD_RestrictionCode"/>
               </gmd:useConstraints>
               <gmd:otherConstraints>
                  <gco:CharacterString>Contacter le propriétaire des données.</gco:CharacterString>
               </gmd:otherConstraints>
            </gmd:MD_LegalConstraints>
         </gmd:resourceConstraints>
         <gmd:spatialRepresentationType>
            <gmd:MD_SpatialRepresentationTypeCode codeListValue="vector"
                                                  codeList="http://standards.iso.org/iso/19139/resources/gmxCodelists.xml#MD_SpatialRepresentationTypeCode"/>
         </gmd:spatialRepresentationType>
         <gmd:spatialResolution>
            <gmd:MD_Resolution>
               <gmd:equivalentScale>
                  <gmd:MD_RepresentativeFraction>
                     <gmd:denominator>
                        <gco:Integer/>
                     </gmd:denominator>
                  </gmd:MD_RepresentativeFraction>
               </gmd:equivalentScale>
            </gmd:MD_Resolution>
         </gmd:spatialResolution>
         <gmd:language>
            <gco:CharacterString>fre</gco:CharacterString>
         </gmd:language>
         <gmd:characterSet>
            <gmd:MD_CharacterSetCode codeListValue="utf8"
                                     codeList="http://standards.iso.org/iso/19139/resources/gmxCodelists.xml#MD_CharacterSetCode"/>
         </gmd:characterSet>
         <gmd:topicCategory>
            <gmd:MD_TopicCategoryCode>imageryBaseMapsEarthCover</gmd:MD_TopicCategoryCode>
         </gmd:topicCategory>
         <gmd:topicCategory>
            <gmd:MD_TopicCategoryCode>biota</gmd:MD_TopicCategoryCode>
         </gmd:topicCategory>
         <gmd:extent>
            <gmd:EX_Extent>
               <gmd:temporalElement>
                  <gmd:EX_TemporalExtent>
                     <gmd:extent>
                        <gml:TimePeriod xmlns:gml="http://www.opengis.net/gml/3.2" gml:id="d73383e435a1053982">
                           <gml:beginPosition>2010-07-08T09:00:00</gml:beginPosition>
                           <gml:endPosition>2010-07-09T00:00:00</gml:endPosition>
                        </gml:TimePeriod>
                     </gmd:extent>
                  </gmd:EX_TemporalExtent>
               </gmd:temporalElement>
            </gmd:EX_Extent>
         </gmd:extent>
         <gmd:extent>
            <gmd:EX_Extent>
               <gmd:geographicElement>
                  <gmd:EX_GeographicBoundingBox>
                     <gmd:westBoundLongitude>
                        <gco:Decimal>1.41435</gco:Decimal>
                     </gmd:westBoundLongitude>
                     <gmd:eastBoundLongitude>
                        <gco:Decimal>1.42422</gco:Decimal>
                     </gmd:eastBoundLongitude>
                     <gmd:southBoundLatitude>
                        <gco:Decimal>42.764025</gco:Decimal>
                     </gmd:southBoundLatitude>
                     <gmd:northBoundLatitude>
                        <gco:Decimal>42.76678</gco:Decimal>
                     </gmd:northBoundLatitude>
                  </gmd:EX_GeographicBoundingBox>
               </gmd:geographicElement>
            </gmd:EX_Extent>
         </gmd:extent>
         <gmd:supplementalInformation>
            <gco:CharacterString>Programme OPA "Occupations Passées, Actuelles et Futures du Haut-Vicdessos" financé par l'OHM (2010-2014)</gco:CharacterString>
         </gmd:supplementalInformation>
      </gmd:MD_DataIdentification>
  </gmd:identificationInfo>
  <gmd:distributionInfo xmlns:gml="http://www.opengis.net/gml">
      <gmd:MD_Distribution>
         <gmd:distributionFormat>
            <gmd:MD_Format>
               <gmd:name>
                  <gco:CharacterString>ZIP</gco:CharacterString>
               </gmd:name>
               <gmd:version gco:nilReason="unknown">
                  <gco:CharacterString/>
               </gmd:version>
            </gmd:MD_Format>
         </gmd:distributionFormat>
         <gmd:transferOptions>
            <gmd:MD_DigitalTransferOptions>
               <gmd:onLine>
                  <gmd:CI_OnlineResource>
                     <gmd:linkage>
                        <gmd:URL>http://w3.ohmpyr.univ-tlse2.fr/programme2010_3.php</gmd:URL>
                     </gmd:linkage>
                     <gmd:protocol>
                        <gco:CharacterString>WWW:LINK-1.0-http--link</gco:CharacterString>
                     </gmd:protocol>
                     <gmd:name>
                        <gco:CharacterString>Projet OHM OPA 2010</gco:CharacterString>
                     </gmd:name>
                     <gmd:description>
                        <gco:CharacterString>Projet OHM OPA 2010</gco:CharacterString>
                     </gmd:description>
                  </gmd:CI_OnlineResource>
               </gmd:onLine>
               <gmd:onLine>
                  <gmd:CI_OnlineResource>
                     <gmd:linkage>
                        <gmd:URL>https://doi.org/10.48579/PRO/PL4RZQ</gmd:URL>
                     </gmd:linkage>
                     <gmd:protocol>
                        <gco:CharacterString>DOI</gco:CharacterString>
                     </gmd:protocol>
                     <gmd:name>
                        <gco:CharacterString>DATA: Wetlands map of the Bassies valley (Haut Vicdessos, Pyrenees, France)</gco:CharacterString>
                     </gmd:name>
                     <gmd:description>
                        <gco:CharacterString>Wetland mapping from in situ surveys made in 2010 and used as validation data for wetland classification.using remotely sensed data.</gco:CharacterString>
                     </gmd:description>
                  </gmd:CI_OnlineResource>
               </gmd:onLine>
               <gmd:onLine>
                  <gmd:CI_OnlineResource>
                     <gmd:linkage>
                        <gmd:URL>https://shs.hal.science/halshs-00752923</gmd:URL>
                     </gmd:linkage>
                     <gmd:protocol>
                        <gco:CharacterString>WWW:LINK-1.0-http--link</gco:CharacterString>
                     </gmd:protocol>
                     <gmd:name>
                        <gco:CharacterString>Cartographie des zones humides de montagnes par télédétection. Potentialités des images à très haute résolution spatiale</gco:CharacterString>
                     </gmd:name>
                     <gmd:description>
                        <gco:CharacterString>Linked scientific article</gco:CharacterString>
                     </gmd:description>
                  </gmd:CI_OnlineResource>
               </gmd:onLine>
            </gmd:MD_DigitalTransferOptions>
         </gmd:transferOptions>
      </gmd:MD_Distribution>
  </gmd:distributionInfo>
  <gmd:dataQualityInfo xmlns:gml="http://www.opengis.net/gml">
      <gmd:DQ_DataQuality>
         <gmd:scope>
            <gmd:DQ_Scope>
               <gmd:level>
                  <gmd:MD_ScopeCode codeListValue="dataset"
                                    codeList="http://standards.iso.org/iso/19139/resources/gmxCodelists.xml#MD_ScopeCode"/>
               </gmd:level>
            </gmd:DQ_Scope>
         </gmd:scope>
         <gmd:lineage>
            <gmd:LI_Lineage>
               <gmd:statement>
                  <gco:CharacterString>Méthodologie : à partir d'une photo aérienne de la vallée de Bassiès et de relevés de terrain, le logiciel MapInfo a été paramétré pour générer automatiquement les polygones correspondant aux 9 types de zones humides distingués sur le site d’étude (Benito et Bonnefoi, 2010) : 
1. mouillères (attribut TYPE_ZH=1), 
2. prairies mixtes (attribut TYPE_ZH=2), 
3. cariçaies (attribut TYPE_ZH=3), 
4. prairies à carex (attribut TYPE_ZH=4), 
5. tourbières à sphaigne (attribut TYPE_ZH=5), 
6. tourbières à carex (attribut TYPE_ZH=6), 
7. prairies à molinies (attribut TYPE_ZH=7), 
8. zones immergées (attribut TYPE_ZH=8), 
9. zones mixtes (attribut TYPE_ZH=9). 
Ref : 
- Benito C. et Bonnefoi S. (2010) Les zones humides de Bassiès. Restitution du travail sur site - Juillet 2010.
- Vacquié L. et Houet T. (2012) Détection et caractérisation des zones humides de montagnes par télédétection: évaluation de l’apport de la Très Haute Résolution Spatiale. Revue Internationale de Géomatique, Vol. 22, 2012/4, 497-518</gco:CharacterString>
               </gmd:statement>
            </gmd:LI_Lineage>
         </gmd:lineage>
      </gmd:DQ_DataQuality>
  </gmd:dataQualityInfo>
</gmd:MD_Metadata>