<?xml version="1.0" encoding="UTF-8"?>
<gmd:MD_Metadata xmlns:gmd="http://www.isotc211.org/2005/gmd"
                 xmlns:gml="http://www.opengis.net/gml/3.2"
                 xmlns:gts="http://www.isotc211.org/2005/gts"
                 xmlns:gco="http://www.isotc211.org/2005/gco"
                 xmlns:xsi="http://www.w3.org/2001/XMLSchema-instance"
                 xsi:schemaLocation="http://www.isotc211.org/2005/gmd http://schemas.opengis.net/csw/2.0.2/profiles/apiso/1.0.0/apiso.xsd">
  <gmd:fileIdentifier>
      <gco:CharacterString>dc971b6b-b9a1-48b7-8eb1-cee86ebe3a83</gco:CharacterString>
  </gmd:fileIdentifier>
  <gmd:language>
      <gmd:LanguageCode codeList="http://www.loc.gov/standards/iso639-2/" codeListValue="fre"/>
  </gmd:language>
  <gmd:characterSet>
      <gmd:MD_CharacterSetCode codeListValue="utf8"
                               codeList="http://standards.iso.org/iso/19139/resources/gmxCodelists.xml#MD_CharacterSetCode"/>
  </gmd:characterSet>
  <gmd:contact>
      <gmd:CI_ResponsibleParty>
         <gmd:individualName>
            <gco:CharacterString>Anne Bonis</gco:CharacterString>
         </gmd:individualName>
         <gmd:organisationName>
            <gco:CharacterString>ECOBIO UMR 6553 CNRS Université de Rennes 1</gco:CharacterString>
         </gmd:organisationName>
         <gmd:positionName>
            <gco:CharacterString>Chargée de recherche</gco:CharacterString>
         </gmd:positionName>
         <gmd:contactInfo>
            <gmd:CI_Contact>
               <gmd:phone>
                  <gmd:CI_Telephone>
                     <gmd:voice gco:nilReason="missing">
                        <gco:CharacterString/>
                     </gmd:voice>
                     <gmd:facsimile gco:nilReason="missing">
                        <gco:CharacterString/>
                     </gmd:facsimile>
                  </gmd:CI_Telephone>
               </gmd:phone>
               <gmd:address>
                  <gmd:CI_Address>
                     <gmd:deliveryPoint gco:nilReason="missing">
                        <gco:CharacterString/>
                     </gmd:deliveryPoint>
                     <gmd:city gco:nilReason="missing">
                        <gco:CharacterString/>
                     </gmd:city>
                     <gmd:administrativeArea gco:nilReason="missing">
                        <gco:CharacterString/>
                     </gmd:administrativeArea>
                     <gmd:postalCode gco:nilReason="missing">
                        <gco:CharacterString/>
                     </gmd:postalCode>
                     <gmd:country gco:nilReason="missing">
                        <gco:CharacterString/>
                     </gmd:country>
                     <gmd:electronicMailAddress gco:nilReason="missing">
                        <gco:CharacterString/>
                     </gmd:electronicMailAddress>
                  </gmd:CI_Address>
               </gmd:address>
            </gmd:CI_Contact>
         </gmd:contactInfo>
         <gmd:role>
            <gmd:CI_RoleCode codeListValue="pointOfContact"
                             codeList="http://standards.iso.org/iso/19139/resources/gmxCodelists.xml#CI_RoleCode"/>
         </gmd:role>
      </gmd:CI_ResponsibleParty>
  </gmd:contact>
  <gmd:dateStamp>
      <gco:DateTime>2017-02-07T11:15:50</gco:DateTime>
  </gmd:dateStamp>
  <gmd:metadataStandardName>
      <gco:CharacterString>ISO 19115:2003/19139</gco:CharacterString>
  </gmd:metadataStandardName>
  <gmd:metadataStandardVersion>
      <gco:CharacterString>1.0</gco:CharacterString>
  </gmd:metadataStandardVersion>
  <gmd:spatialRepresentationInfo>
      <gmd:MD_GridSpatialRepresentation>
         <gmd:numberOfDimensions>
            <gco:Integer>2</gco:Integer>
         </gmd:numberOfDimensions>
         <gmd:axisDimensionProperties>
            <gmd:MD_Dimension>
               <gmd:dimensionName>
                  <gmd:MD_DimensionNameTypeCode codeListValue="row"
                                                codeList="http://standards.iso.org/iso/19139/resources/gmxCodelists.xml#MD_DimensionNameTypeCode"/>
               </gmd:dimensionName>
               <gmd:dimensionSize>
                  <gco:Integer>6245</gco:Integer>
               </gmd:dimensionSize>
               <gmd:resolution>
                  <gco:Measure uom="">30</gco:Measure>
               </gmd:resolution>
            </gmd:MD_Dimension>
         </gmd:axisDimensionProperties>
         <gmd:axisDimensionProperties>
            <gmd:MD_Dimension>
               <gmd:dimensionName>
                  <gmd:MD_DimensionNameTypeCode codeListValue="column"
                                                codeList="http://standards.iso.org/iso/19139/resources/gmxCodelists.xml#MD_DimensionNameTypeCode"/>
               </gmd:dimensionName>
               <gmd:dimensionSize>
                  <gco:Integer>8143</gco:Integer>
               </gmd:dimensionSize>
               <gmd:resolution>
                  <gco:Measure uom="">30</gco:Measure>
               </gmd:resolution>
            </gmd:MD_Dimension>
         </gmd:axisDimensionProperties>
         <gmd:axisDimensionProperties>
            <gmd:MD_Dimension>
               <gmd:dimensionName>
                  <gmd:MD_DimensionNameTypeCode codeListValue="vertical"
                                                codeList="http://standards.iso.org/iso/19139/resources/gmxCodelists.xml#MD_DimensionNameTypeCode"/>
               </gmd:dimensionName>
               <gmd:dimensionSize>
                  <gco:Integer/>
               </gmd:dimensionSize>
               <gmd:resolution>
                  <gco:Measure uom=""/>
               </gmd:resolution>
            </gmd:MD_Dimension>
         </gmd:axisDimensionProperties>
         <gmd:cellGeometry>
            <gmd:MD_CellGeometryCode codeListValue="area"
                                     codeList="http://standards.iso.org/iso/19139/resources/gmxCodelists.xml#MD_CellGeometryCode"/>
         </gmd:cellGeometry>
         <gmd:transformationParameterAvailability>
            <gco:Boolean/>
         </gmd:transformationParameterAvailability>
      </gmd:MD_GridSpatialRepresentation>
  </gmd:spatialRepresentationInfo>
  <gmd:referenceSystemInfo>
      <gmd:MD_ReferenceSystem>
         <gmd:referenceSystemIdentifier>
            <gmd:RS_Identifier>
               <gmd:code>
                  <gco:CharacterString>UTM 30N</gco:CharacterString>
               </gmd:code>
            </gmd:RS_Identifier>
         </gmd:referenceSystemIdentifier>
      </gmd:MD_ReferenceSystem>
  </gmd:referenceSystemInfo>
  <gmd:identificationInfo>
      <gmd:MD_DataIdentification>
         <gmd:citation>
            <gmd:CI_Citation>
               <gmd:title>
                  <gco:CharacterString>Image Landsat-8 Marais Atlantique - 08/12/2013</gco:CharacterString>
               </gmd:title>
               <gmd:date>
                  <gmd:CI_Date>
                     <gmd:date>
                        <gco:DateTime>2015-08-31T09:00:00</gco:DateTime>
                     </gmd:date>
                     <gmd:dateType>
                        <gmd:CI_DateTypeCode codeListValue="publication"
                                             codeList="http://standards.iso.org/iso/19139/resources/gmxCodelists.xml#CI_DateTypeCode"/>
                     </gmd:dateType>
                  </gmd:CI_Date>
               </gmd:date>
               <gmd:edition gco:nilReason="missing">
                  <gco:CharacterString/>
               </gmd:edition>
            </gmd:CI_Citation>
         </gmd:citation>
         <gmd:abstract>
            <gco:CharacterString>Image Landsat-8 corrigée géométriquement et atmosphériquement (FLAASH)</gco:CharacterString>
         </gmd:abstract>
         <gmd:purpose>
            <gco:CharacterString>Recherche scientifique</gco:CharacterString>
         </gmd:purpose>
         <gmd:status>
            <gmd:MD_ProgressCode codeListValue="completed"
                                 codeList="http://standards.iso.org/iso/19139/resources/gmxCodelists.xml#MD_ProgressCode"/>
         </gmd:status>
         <gmd:pointOfContact>
            <gmd:CI_ResponsibleParty>
               <gmd:individualName>
                  <gco:CharacterString>Sébastien Rapinel</gco:CharacterString>
               </gmd:individualName>
               <gmd:organisationName>
                  <gco:CharacterString>ECOBIO UMR 6553 CNRS Université de Rennes 1</gco:CharacterString>
               </gmd:organisationName>
               <gmd:positionName>
                  <gco:CharacterString>Chercheur contractuel</gco:CharacterString>
               </gmd:positionName>
               <gmd:contactInfo>
                  <gmd:CI_Contact>
                     <gmd:phone>
                        <gmd:CI_Telephone>
                           <gmd:voice gco:nilReason="missing">
                              <gco:CharacterString/>
                           </gmd:voice>
                           <gmd:facsimile gco:nilReason="missing">
                              <gco:CharacterString/>
                           </gmd:facsimile>
                        </gmd:CI_Telephone>
                     </gmd:phone>
                     <gmd:address>
                        <gmd:CI_Address>
                           <gmd:deliveryPoint>
                              <gco:CharacterString>avenue Général Leclerc</gco:CharacterString>
                           </gmd:deliveryPoint>
                           <gmd:city>
                              <gco:CharacterString>Rennes</gco:CharacterString>
                           </gmd:city>
                           <gmd:administrativeArea gco:nilReason="missing">
                              <gco:CharacterString/>
                           </gmd:administrativeArea>
                           <gmd:postalCode>
                              <gco:CharacterString>35000</gco:CharacterString>
                           </gmd:postalCode>
                           <gmd:country gco:nilReason="missing">
                              <gco:CharacterString/>
                           </gmd:country>
                           <gmd:electronicMailAddress>
                              <gco:CharacterString>sebastien.rapinel@univ-rennes1.fr</gco:CharacterString>
                           </gmd:electronicMailAddress>
                        </gmd:CI_Address>
                     </gmd:address>
                  </gmd:CI_Contact>
               </gmd:contactInfo>
               <gmd:role>
                  <gmd:CI_RoleCode codeListValue="author"
                                   codeList="http://standards.iso.org/iso/19139/resources/gmxCodelists.xml#CI_RoleCode"/>
               </gmd:role>
            </gmd:CI_ResponsibleParty>
         </gmd:pointOfContact>
         <gmd:resourceMaintenance>
            <gmd:MD_MaintenanceInformation>
               <gmd:maintenanceAndUpdateFrequency>
                  <gmd:MD_MaintenanceFrequencyCode codeListValue="notPlanned"
                                                   codeList="http://standards.iso.org/iso/19139/resources/gmxCodelists.xml#MD_MaintenanceFrequencyCode"/>
               </gmd:maintenanceAndUpdateFrequency>
            </gmd:MD_MaintenanceInformation>
         </gmd:resourceMaintenance>
         <gmd:graphicOverview>
            <gmd:MD_BrowseGraphic>
               <gmd:fileName gco:nilReason="missing">
                  <gco:CharacterString/>
               </gmd:fileName>
               <gmd:fileDescription>
                  <gco:CharacterString>thumbnail</gco:CharacterString>
               </gmd:fileDescription>
            </gmd:MD_BrowseGraphic>
         </gmd:graphicOverview>
         <gmd:graphicOverview>
            <gmd:MD_BrowseGraphic>
               <gmd:fileName gco:nilReason="missing">
                  <gco:CharacterString/>
               </gmd:fileName>
               <gmd:fileDescription>
                  <gco:CharacterString>large_thumbnail</gco:CharacterString>
               </gmd:fileDescription>
            </gmd:MD_BrowseGraphic>
         </gmd:graphicOverview>
         <gmd:descriptiveKeywords>
            <gmd:MD_Keywords>
               <gmd:keyword>
                  <gco:CharacterString>satellite</gco:CharacterString>
               </gmd:keyword>
               <gmd:type>
                  <gmd:MD_KeywordTypeCode codeListValue="theme" codeList="./resources/codeList.xml#MD_KeywordTypeCode"/>
               </gmd:type>
            </gmd:MD_Keywords>
         </gmd:descriptiveKeywords>
         <gmd:descriptiveKeywords>
            <gmd:MD_Keywords>
               <gmd:keyword>
                  <gco:CharacterString>World</gco:CharacterString>
               </gmd:keyword>
               <gmd:type>
                  <gmd:MD_KeywordTypeCode codeListValue="place" codeList="./resources/codeList.xml#MD_KeywordTypeCode"/>
               </gmd:type>
            </gmd:MD_Keywords>
         </gmd:descriptiveKeywords>
         <gmd:descriptiveKeywords>
            <gmd:MD_Keywords>
               <gmd:type>
                  <gmd:MD_KeywordTypeCode codeList="http://www.isotc211.org/2005/resources/codeList.xml#MD_KeywordTypeCode"
                                          codeListValue="theme"/>
               </gmd:type>
               <gmd:thesaurusName>
                  <gmd:CI_Citation>
                     <gmd:title>
                        <gco:CharacterString>GEMET - INSPIRE themes, version 1.0</gco:CharacterString>
                     </gmd:title>
                     <gmd:date>
                        <gmd:CI_Date>
                           <gmd:date>
                              <gco:Date>2008-06-01</gco:Date>
                           </gmd:date>
                           <gmd:dateType>
                              <gmd:CI_DateTypeCode codeList="http://standards.iso.org/iso/19139/resources/gmxCodelists.xml#CI_DateTypeCode"
                                                   codeListValue="publication"/>
                           </gmd:dateType>
                        </gmd:CI_Date>
                     </gmd:date>
                     <gmd:identifier>
                        <gmd:MD_Identifier>
                           <gmd:code>
                              <gmx:Anchor xmlns:gmx="http://www.isotc211.org/2005/gmx"
                                          xmlns:xlink="http://www.w3.org/1999/xlink"
                                          xlink:href="http://www.osuris.fr/geonetwork/srv/eng/thesaurus.download?ref=external.theme.inspire-theme">geonetwork.thesaurus.external.theme.inspire-theme</gmx:Anchor>
                           </gmd:code>
                        </gmd:MD_Identifier>
                     </gmd:identifier>
                  </gmd:CI_Citation>
               </gmd:thesaurusName>
            </gmd:MD_Keywords>
         </gmd:descriptiveKeywords>
         <gmd:resourceConstraints>
            <gmd:MD_LegalConstraints>
               <gmd:accessConstraints>
                  <gmd:MD_RestrictionCode codeListValue="copyright"
                                          codeList="http://standards.iso.org/iso/19139/resources/gmxCodelists.xml#MD_RestrictionCode"/>
               </gmd:accessConstraints>
               <gmd:otherConstraints gco:nilReason="missing">
                  <gco:CharacterString/>
               </gmd:otherConstraints>
            </gmd:MD_LegalConstraints>
         </gmd:resourceConstraints>
         <gmd:spatialRepresentationType>
            <gmd:MD_SpatialRepresentationTypeCode codeListValue="grid"
                                                  codeList="http://standards.iso.org/iso/19139/resources/gmxCodelists.xml#MD_SpatialRepresentationTypeCode"/>
         </gmd:spatialRepresentationType>
         <gmd:spatialResolution>
            <gmd:MD_Resolution>
               <gmd:equivalentScale>
                  <gmd:MD_RepresentativeFraction>
                     <gmd:denominator>
                        <gco:Integer>50000</gco:Integer>
                     </gmd:denominator>
                  </gmd:MD_RepresentativeFraction>
               </gmd:equivalentScale>
            </gmd:MD_Resolution>
         </gmd:spatialResolution>
         <gmd:language>
            <gco:CharacterString>eng</gco:CharacterString>
         </gmd:language>
         <gmd:characterSet>
            <gmd:MD_CharacterSetCode codeListValue="utf8"
                                     codeList="http://standards.iso.org/iso/19139/resources/gmxCodelists.xml#MD_CharacterSetCode"/>
         </gmd:characterSet>
         <gmd:topicCategory>
            <gmd:MD_TopicCategoryCode>imageryBaseMapsEarthCover</gmd:MD_TopicCategoryCode>
         </gmd:topicCategory>
         <gmd:extent>
            <gmd:EX_Extent>
               <gmd:temporalElement>
                  <gmd:EX_TemporalExtent>
                     <gmd:extent>
                        <gml:TimePeriod gml:id="d263051e515a1052958">
                           <gml:beginPosition>2013-12-08</gml:beginPosition>
                           <gml:endPosition>2013-12-08</gml:endPosition>
                        </gml:TimePeriod>
                     </gmd:extent>
                  </gmd:EX_TemporalExtent>
               </gmd:temporalElement>
            </gmd:EX_Extent>
         </gmd:extent>
         <gmd:extent>
            <gmd:EX_Extent>
               <gmd:geographicElement>
                  <gmd:EX_GeographicBoundingBox>
                     <gmd:westBoundLongitude>
                        <gco:Decimal>-2.637</gco:Decimal>
                     </gmd:westBoundLongitude>
                     <gmd:eastBoundLongitude>
                        <gco:Decimal>-0.1287</gco:Decimal>
                     </gmd:eastBoundLongitude>
                     <gmd:southBoundLatitude>
                        <gco:Decimal>45.431</gco:Decimal>
                     </gmd:southBoundLatitude>
                     <gmd:northBoundLatitude>
                        <gco:Decimal>47.662</gco:Decimal>
                     </gmd:northBoundLatitude>
                  </gmd:EX_GeographicBoundingBox>
               </gmd:geographicElement>
            </gmd:EX_Extent>
         </gmd:extent>
         <gmd:supplementalInformation gco:nilReason="missing">
            <gco:CharacterString/>
         </gmd:supplementalInformation>
      </gmd:MD_DataIdentification>
  </gmd:identificationInfo>
  <gmd:distributionInfo>
      <gmd:MD_Distribution>
         <gmd:transferOptions>
            <gmd:MD_DigitalTransferOptions>
               <gmd:onLine>
                  <gmd:CI_OnlineResource>
                     <gmd:linkage>
                        <gmd:URL/>
                     </gmd:linkage>
                     <gmd:protocol>
                        <gco:CharacterString>WWW:LINK-1.0-http--link</gco:CharacterString>
                     </gmd:protocol>
                     <gmd:name gco:nilReason="missing">
                        <gco:CharacterString/>
                     </gmd:name>
                     <gmd:description gco:nilReason="missing">
                        <gco:CharacterString/>
                     </gmd:description>
                  </gmd:CI_OnlineResource>
               </gmd:onLine>
               <gmd:onLine>
                  <gmd:CI_OnlineResource>
                     <gmd:linkage>
                        <gmd:URL>http://www.osuris.fr/geonetwork/srv/fre/resources.get?uuid=dc971b6b-b9a1-48b7-8eb1-cee86ebe3a83&amp;fname=&amp;access=public</gmd:URL>
                     </gmd:linkage>
                     <gmd:protocol>
                        <gco:CharacterString>WWW:DOWNLOAD-1.0-http--download</gco:CharacterString>
                     </gmd:protocol>
                     <gmd:name>
                        <gmx:MimeFileType xmlns:gmx="http://www.isotc211.org/2005/gmx" type=""/>
                     </gmd:name>
                     <gmd:description>
                        <gco:CharacterString/>
                     </gmd:description>
                  </gmd:CI_OnlineResource>
               </gmd:onLine>
            </gmd:MD_DigitalTransferOptions>
         </gmd:transferOptions>
      </gmd:MD_Distribution>
  </gmd:distributionInfo>
  <gmd:dataQualityInfo>
      <gmd:DQ_DataQuality>
         <gmd:scope>
            <gmd:DQ_Scope>
               <gmd:level>
                  <gmd:MD_ScopeCode codeListValue="map"
                                    codeList="http://standards.iso.org/iso/19139/resources/gmxCodelists.xml#MD_ScopeCode"/>
               </gmd:level>
            </gmd:DQ_Scope>
         </gmd:scope>
         <gmd:lineage>
            <gmd:LI_Lineage>
               <gmd:statement gco:nilReason="missing">
                  <gco:CharacterString/>
               </gmd:statement>
            </gmd:LI_Lineage>
         </gmd:lineage>
      </gmd:DQ_DataQuality>
  </gmd:dataQualityInfo>
</gmd:MD_Metadata>